<markdown_skeleton_root>
  <block_element>
    <ArrayOfMarkdownBlockBase xmlns:xsd="http://www.w3.org/2001/XMLSchema" xmlns:xsi="http://www.w3.org/2001/XMLSchema-instance">
      <MarkdownBlockBase
        xsi:type="MarkdownParagraphBlock"
        item_id="389ed344-f2e2-47a5-8d02-b25bc3b57386"
        item_type="NormalParagraph"
        item_footer=""
        trans_unit_id="389ed344-f2e2-47a5-8d02-b25bc3b57386">
        <Lines>
          <MarkdownLine>
            <LineId>41b8bee4-18db-4ec5-b7e9-88396167e304</LineId>
            <paragraph_segments>
              <MarkdownSegment
                trans_unit_id="101">
                <SegmentId>5d10eec1-060c-407e-93ea-68b9b9efac28</SegmentId>
                <InternalNormalItem
                  internal_item_id="1"
                  internal_item_parent_id="101"
                  trans_unit_id="101-1"
                  internal_item_type="Normal">
                  <internal_items />
                </InternalNormalItem>
              </MarkdownSegment>
            </paragraph_segments>
            <PrefixWSLength>0</PrefixWSLength>
            <SuffixWSLength>0</SuffixWSLength>
          </MarkdownLine>
          <MarkdownLine>
            <LineId>48ed3821-552d-45f0-abb1-81eefff1bc34</LineId>
            <paragraph_segments>
              <MarkdownSegment
                trans_unit_id="102">
                <SegmentId>92967c97-55d5-411b-847b-d32b92cd8bc4</SegmentId>
                <InternalNormalItem
                  internal_item_id="1"
                  internal_item_parent_id="102"
                  trans_unit_id="102-1"
                  internal_item_type="Normal">
                  <internal_items />
                </InternalNormalItem>
              </MarkdownSegment>
            </paragraph_segments>
            <PrefixWSLength>0</PrefixWSLength>
            <SuffixWSLength>0</SuffixWSLength>
          </MarkdownLine>
        </Lines>
        <paragraph_segments>
          <MarkdownSegment
            trans_unit_id="101">
            <SegmentId>5d10eec1-060c-407e-93ea-68b9b9efac28</SegmentId>
            <InternalNormalItem
              internal_item_id="1"
              internal_item_parent_id="101"
              trans_unit_id="101-1"
              internal_item_type="Normal">
              <internal_items />
            </InternalNormalItem>
          </MarkdownSegment>
          <MarkdownSegment
            trans_unit_id="102">
            <SegmentId>92967c97-55d5-411b-847b-d32b92cd8bc4</SegmentId>
            <InternalNormalItem
              internal_item_id="1"
              internal_item_parent_id="102"
              trans_unit_id="102-1"
              internal_item_type="Normal">
              <internal_items />
            </InternalNormalItem>
          </MarkdownSegment>
        </paragraph_segments>
      </MarkdownBlockBase>
      <MarkdownBlockBase
        xsi:type="MarkdownHeaderBlock"
        item_id="7eaf6bb9-5a65-4b73-ba54-4266bbcf6b1a"
        item_type="Header"
        item_footer="footer_not_set"
        trans_unit_id="7eaf6bb9-5a65-4b73-ba54-4266bbcf6b1a">
        <segment
          trans_unit_id="103">
          <SegmentId>91733937-eb1d-40ad-a879-d822b96f7368</SegmentId>
          <InternalNormalItem
            internal_item_id="1"
            internal_item_parent_id="103"
            trans_unit_id="103-1"
            internal_item_type="Normal">
            <internal_items />
          </InternalNormalItem>
        </segment>
        <header_type>Star</header_type>
        <header_level>1</header_level>
      </MarkdownBlockBase>
      <MarkdownBlockBase
        xsi:type="MarkdownParagraphBlock"
        item_id="4e36d252-053d-4c36-a382-e579d57f5ee9"
        item_type="NormalParagraph"
        item_footer=""
        trans_unit_id="4e36d252-053d-4c36-a382-e579d57f5ee9">
        <Lines>
          <MarkdownLine>
            <LineId>0cd24eea-1581-4225-8afe-4ed0d4507697</LineId>
            <paragraph_segments>
              <MarkdownSegment
                trans_unit_id="104">
                <SegmentId>e7bb255b-04da-46bf-afd4-772b4f064889</SegmentId>
                <InternalNormalItem
                  internal_item_id="1"
                  internal_item_parent_id="104"
                  trans_unit_id="104-1"
                  internal_item_type="Normal">
                  <internal_items />
                </InternalNormalItem>
              </MarkdownSegment>
              <MarkdownSegment
                trans_unit_id="105">
                <SegmentId>f7d8a9c1-7c02-43f5-bb31-0d8412cf616c</SegmentId>
                <InternalNormalItem
                  internal_item_id="1"
                  internal_item_parent_id="105"
                  trans_unit_id="105-1"
                  internal_item_type="Normal">
                  <internal_items />
                </InternalNormalItem>
              </MarkdownSegment>
            </paragraph_segments>
            <PrefixWSLength>0</PrefixWSLength>
            <SuffixWSLength>0</SuffixWSLength>
          </MarkdownLine>
        </Lines>
        <paragraph_segments>
          <MarkdownSegment
            trans_unit_id="104">
            <SegmentId>e7bb255b-04da-46bf-afd4-772b4f064889</SegmentId>
            <InternalNormalItem
              internal_item_id="1"
              internal_item_parent_id="104"
              trans_unit_id="104-1"
              internal_item_type="Normal">
              <internal_items />
            </InternalNormalItem>
          </MarkdownSegment>
          <MarkdownSegment
            trans_unit_id="105">
            <SegmentId>f7d8a9c1-7c02-43f5-bb31-0d8412cf616c</SegmentId>
            <InternalNormalItem
              internal_item_id="1"
              internal_item_parent_id="105"
              trans_unit_id="105-1"
              internal_item_type="Normal">
              <internal_items />
            </InternalNormalItem>
          </MarkdownSegment>
        </paragraph_segments>
      </MarkdownBlockBase>
      <MarkdownBlockBase
        xsi:type="MarkdownParagraphBlock"
        item_id="0b4d89e7-f32c-43bd-8fd3-0c98f687c808"
        item_type="NormalParagraph"
        item_footer=""
        trans_unit_id="0b4d89e7-f32c-43bd-8fd3-0c98f687c808">
        <Lines>
          <MarkdownLine>
            <LineId>7d24c05e-15c2-48cf-ab7c-5c56635fa1c2</LineId>
            <paragraph_segments>
              <MarkdownSegment
                trans_unit_id="106">
                <SegmentId>8f78309c-6225-43d6-8d09-eb64dfe2b5a2</SegmentId>
                <InternalNormalItem
                  internal_item_id="1"
                  internal_item_parent_id="106"
                  trans_unit_id="106-1"
                  internal_item_type="Normal">
                  <internal_items />
                </InternalNormalItem>
                <LinkItem
                  internal_item_id="2"
                  internal_item_parent_id="106"
                  trans_unit_id="106-2"
                  internal_item_type="Link">
                  <internal_items />
                  <internal_link_type>Inline</internal_link_type>
                  <internal_link_text>Windows-based containers: Modern app development with enterprise-grade control</internal_link_text>
                  <internal_link_url>https://youtu.be/Ryx3o0rD5lY</internal_link_url>
                  <internal_link_title />
                </LinkItem>
                <InternalNormalItem
                  internal_item_id="3"
                  internal_item_parent_id="106"
                  trans_unit_id="106-3"
                  internal_item_type="Normal">
                  <internal_items />
                </InternalNormalItem>
              </MarkdownSegment>
            </paragraph_segments>
            <PrefixWSLength>0</PrefixWSLength>
            <SuffixWSLength>0</SuffixWSLength>
          </MarkdownLine>
        </Lines>
        <paragraph_segments>
          <MarkdownSegment
            trans_unit_id="106">
            <SegmentId>8f78309c-6225-43d6-8d09-eb64dfe2b5a2</SegmentId>
            <InternalNormalItem
              internal_item_id="1"
              internal_item_parent_id="106"
              trans_unit_id="106-1"
              internal_item_type="Normal">
              <internal_items />
            </InternalNormalItem>
            <LinkItem
              internal_item_id="2"
              internal_item_parent_id="106"
              trans_unit_id="106-2"
              internal_item_type="Link">
              <internal_items />
              <internal_link_type>Inline</internal_link_type>
              <internal_link_text>Windows-based containers: Modern app development with enterprise-grade control</internal_link_text>
              <internal_link_url>https://youtu.be/Ryx3o0rD5lY</internal_link_url>
              <internal_link_title />
            </LinkItem>
            <InternalNormalItem
              internal_item_id="3"
              internal_item_parent_id="106"
              trans_unit_id="106-3"
              internal_item_type="Normal">
              <internal_items />
            </InternalNormalItem>
          </MarkdownSegment>
        </paragraph_segments>
      </MarkdownBlockBase>
      <MarkdownBlockBase
        xsi:type="MarkdownHeaderBlock"
        item_id="772cf397-490c-46dd-ae32-620326ea1d80"
        item_type="Header"
        item_footer="footer_not_set"
        trans_unit_id="772cf397-490c-46dd-ae32-620326ea1d80">
        <segment
          trans_unit_id="107">
          <SegmentId>0308f594-44df-4cc3-a517-52263f0ea95d</SegmentId>
          <InternalNormalItem
            internal_item_id="1"
            internal_item_parent_id="107"
            trans_unit_id="107-1"
            internal_item_type="Normal">
            <internal_items />
          </InternalNormalItem>
        </segment>
        <header_type>Star</header_type>
        <header_level>2</header_level>
      </MarkdownBlockBase>
      <MarkdownBlockBase
        xsi:type="MarkdownParagraphBlock"
        item_id="0085a5af-4073-4241-9286-48b4cbafa0ff"
        item_type="NormalParagraph"
        item_footer=""
        trans_unit_id="0085a5af-4073-4241-9286-48b4cbafa0ff">
        <Lines>
          <MarkdownLine>
            <LineId>e8607c05-ae36-456e-b20d-92de31909176</LineId>
            <paragraph_segments>
              <MarkdownSegment
                trans_unit_id="108">
                <SegmentId>b85a1dc8-1871-4c32-a80e-e9c957c90cc8</SegmentId>
                <InternalNormalItem
                  internal_item_id="1"
                  internal_item_parent_id="108"
                  trans_unit_id="108-1"
                  internal_item_type="Normal">
                  <internal_items />
                </InternalNormalItem>
              </MarkdownSegment>
            </paragraph_segments>
            <PrefixWSLength>0</PrefixWSLength>
            <SuffixWSLength>0</SuffixWSLength>
          </MarkdownLine>
        </Lines>
        <paragraph_segments>
          <MarkdownSegment
            trans_unit_id="108">
            <SegmentId>b85a1dc8-1871-4c32-a80e-e9c957c90cc8</SegmentId>
            <InternalNormalItem
              internal_item_id="1"
              internal_item_parent_id="108"
              trans_unit_id="108-1"
              internal_item_type="Normal">
              <internal_items />
            </InternalNormalItem>
          </MarkdownSegment>
        </paragraph_segments>
      </MarkdownBlockBase>
      <MarkdownBlockBase
        xsi:type="MarkdownParagraphBlock"
        item_id="9a1a1c7e-cd34-4db6-aaac-472df7a47c0e"
        item_type="NormalParagraph"
        item_footer=""
        trans_unit_id="9a1a1c7e-cd34-4db6-aaac-472df7a47c0e">
        <Lines>
          <MarkdownLine>
            <LineId>2277c324-b586-402c-97a9-10f925cd3731</LineId>
            <paragraph_segments>
              <MarkdownSegment
                trans_unit_id="109">
                <SegmentId>04181ece-e9ec-4419-9bc8-ddd550f968b4</SegmentId>
                <InternalNormalItem
                  internal_item_id="1"
                  internal_item_parent_id="109"
                  trans_unit_id="109-1"
                  internal_item_type="Normal">
                  <internal_items />
                </InternalNormalItem>
              </MarkdownSegment>
              <MarkdownSegment
                trans_unit_id="110">
                <SegmentId>24c74a97-8665-4eeb-9431-f616744aafa1</SegmentId>
                <InternalNormalItem
                  internal_item_id="1"
                  internal_item_parent_id="110"
                  trans_unit_id="110-1"
                  internal_item_type="Normal">
                  <internal_items />
                </InternalNormalItem>
              </MarkdownSegment>
            </paragraph_segments>
            <PrefixWSLength>0</PrefixWSLength>
            <SuffixWSLength>0</SuffixWSLength>
          </MarkdownLine>
        </Lines>
        <paragraph_segments>
          <MarkdownSegment
            trans_unit_id="109">
            <SegmentId>04181ece-e9ec-4419-9bc8-ddd550f968b4</SegmentId>
            <InternalNormalItem
              internal_item_id="1"
              internal_item_parent_id="109"
              trans_unit_id="109-1"
              internal_item_type="Normal">
              <internal_items />
            </InternalNormalItem>
          </MarkdownSegment>
          <MarkdownSegment
            trans_unit_id="110">
            <SegmentId>24c74a97-8665-4eeb-9431-f616744aafa1</SegmentId>
            <InternalNormalItem
              internal_item_id="1"
              internal_item_parent_id="110"
              trans_unit_id="110-1"
              internal_item_type="Normal">
              <internal_items />
            </InternalNormalItem>
          </MarkdownSegment>
        </paragraph_segments>
      </MarkdownBlockBase>
      <MarkdownBlockBase
        xsi:type="MarkdownParagraphBlock"
        item_id="034744c2-a970-47fc-93f7-18f5729b8493"
        item_type="NormalParagraph"
        item_footer=""
        trans_unit_id="034744c2-a970-47fc-93f7-18f5729b8493">
        <Lines>
          <MarkdownLine>
            <LineId>ebc190b6-2f6b-4d24-8f9a-6da97ca7b141</LineId>
            <paragraph_segments>
              <MarkdownSegment
                trans_unit_id="111">
                <SegmentId>9e87dde9-635d-4280-97de-47f1b3196a2d</SegmentId>
                <InternalNormalItem
                  internal_item_id="1"
                  internal_item_parent_id="111"
                  trans_unit_id="111-1"
                  internal_item_type="Normal">
                  <internal_items />
                </InternalNormalItem>
              </MarkdownSegment>
              <MarkdownSegment
                trans_unit_id="112">
                <SegmentId>4badff1d-d4b3-497a-89ee-e84dfbd709e7</SegmentId>
                <InternalNormalItem
                  internal_item_id="1"
                  internal_item_parent_id="112"
                  trans_unit_id="112-1"
                  internal_item_type="Normal">
                  <internal_items />
                </InternalNormalItem>
                <LinkItem
                  internal_item_id="2"
                  internal_item_parent_id="112"
                  trans_unit_id="112-2"
                  internal_item_type="Link">
                  <internal_items />
                  <internal_link_type>Inline</internal_link_type>
                  <internal_link_text>Docker</internal_link_text>
                  <internal_link_url>https://www.docker.com/</internal_link_url>
                  <internal_link_title />
                </LinkItem>
                <InternalNormalItem
                  internal_item_id="3"
                  internal_item_parent_id="112"
                  trans_unit_id="112-3"
                  internal_item_type="Normal">
                  <internal_items />
                </InternalNormalItem>
              </MarkdownSegment>
            </paragraph_segments>
            <PrefixWSLength>0</PrefixWSLength>
            <SuffixWSLength>0</SuffixWSLength>
          </MarkdownLine>
        </Lines>
        <paragraph_segments>
          <MarkdownSegment
            trans_unit_id="111">
            <SegmentId>9e87dde9-635d-4280-97de-47f1b3196a2d</SegmentId>
            <InternalNormalItem
              internal_item_id="1"
              internal_item_parent_id="111"
              trans_unit_id="111-1"
              internal_item_type="Normal">
              <internal_items />
            </InternalNormalItem>
          </MarkdownSegment>
          <MarkdownSegment
            trans_unit_id="112">
            <SegmentId>4badff1d-d4b3-497a-89ee-e84dfbd709e7</SegmentId>
            <InternalNormalItem
              internal_item_id="1"
              internal_item_parent_id="112"
              trans_unit_id="112-1"
              internal_item_type="Normal">
              <internal_items />
            </InternalNormalItem>
            <LinkItem
              internal_item_id="2"
              internal_item_parent_id="112"
              trans_unit_id="112-2"
              internal_item_type="Link">
              <internal_items />
              <internal_link_type>Inline</internal_link_type>
              <internal_link_text>Docker</internal_link_text>
              <internal_link_url>https://www.docker.com/</internal_link_url>
              <internal_link_title />
            </LinkItem>
            <InternalNormalItem
              internal_item_id="3"
              internal_item_parent_id="112"
              trans_unit_id="112-3"
              internal_item_type="Normal">
              <internal_items />
            </InternalNormalItem>
          </MarkdownSegment>
        </paragraph_segments>
      </MarkdownBlockBase>
      <MarkdownBlockBase
        xsi:type="MarkdownHeaderBlock"
        item_id="259134cf-804d-4c46-81eb-d4d1f91787f8"
        item_type="Header"
        item_footer="footer_not_set"
        trans_unit_id="259134cf-804d-4c46-81eb-d4d1f91787f8">
        <segment
          trans_unit_id="113">
          <SegmentId>691dbd5e-4c94-4743-aad9-e1a03c1116f6</SegmentId>
          <InternalNormalItem
            internal_item_id="1"
            internal_item_parent_id="113"
            trans_unit_id="113-1"
            internal_item_type="Normal">
            <internal_items />
          </InternalNormalItem>
        </segment>
        <header_type>Star</header_type>
        <header_level>2</header_level>
      </MarkdownBlockBase>
      <MarkdownBlockBase
        xsi:type="MarkdownParagraphBlock"
        item_id="c2375e49-f969-4632-88ea-8303136c9010"
        item_type="NormalParagraph"
        item_footer=""
        trans_unit_id="c2375e49-f969-4632-88ea-8303136c9010">
        <Lines>
          <MarkdownLine>
            <LineId>dbb73893-719b-4c5d-8598-c7696e2898bb</LineId>
            <paragraph_segments>
              <MarkdownSegment
                trans_unit_id="114">
                <SegmentId>34f43aab-a46e-4649-9bfa-0b4f17742822</SegmentId>
                <InternalNormalItem
                  internal_item_id="1"
                  internal_item_parent_id="114"
                  trans_unit_id="114-1"
                  internal_item_type="Normal">
                  <internal_items />
                </InternalNormalItem>
              </MarkdownSegment>
              <MarkdownSegment
                trans_unit_id="115">
                <SegmentId>0a2b1da9-9bdf-4eae-91a9-793b63226b41</SegmentId>
                <InternalNormalItem
                  internal_item_id="1"
                  internal_item_parent_id="115"
                  trans_unit_id="115-1"
                  internal_item_type="Normal">
                  <internal_items />
                </InternalNormalItem>
              </MarkdownSegment>
              <MarkdownSegment
                trans_unit_id="116">
                <SegmentId>413aa90e-9499-4933-997d-5acd37d37141</SegmentId>
                <InternalNormalItem
                  internal_item_id="1"
                  internal_item_parent_id="116"
                  trans_unit_id="116-1"
                  internal_item_type="Normal">
                  <internal_items />
                </InternalNormalItem>
              </MarkdownSegment>
            </paragraph_segments>
            <PrefixWSLength>0</PrefixWSLength>
            <SuffixWSLength>2</SuffixWSLength>
          </MarkdownLine>
          <MarkdownLine>
            <LineId>d6c5ebe2-d671-46a6-be65-4f223e43c72e</LineId>
            <paragraph_segments>
              <MarkdownSegment
                trans_unit_id="117">
                <SegmentId>7ae71da2-fcba-40ba-b287-6416f2dde263</SegmentId>
                <LinkItem
                  internal_item_id="1"
                  internal_item_parent_id="117"
                  trans_unit_id="117-1"
                  internal_item_type="Link">
                  <internal_items />
                  <internal_link_type>Inline</internal_link_type>
                  <internal_link_text>This blog post</internal_link_text>
                  <internal_link_url>http://azure.microsoft.com/blog/2015/08/17/containers-docker-windows-and-trends/</internal_link_url>
                  <internal_link_title />
                </LinkItem>
                <InternalNormalItem
                  internal_item_id="2"
                  internal_item_parent_id="117"
                  trans_unit_id="117-2"
                  internal_item_type="Normal">
                  <internal_items />
                </InternalNormalItem>
              </MarkdownSegment>
            </paragraph_segments>
            <PrefixWSLength>0</PrefixWSLength>
            <SuffixWSLength>0</SuffixWSLength>
          </MarkdownLine>
        </Lines>
        <paragraph_segments>
          <MarkdownSegment
            trans_unit_id="114">
            <SegmentId>34f43aab-a46e-4649-9bfa-0b4f17742822</SegmentId>
            <InternalNormalItem
              internal_item_id="1"
              internal_item_parent_id="114"
              trans_unit_id="114-1"
              internal_item_type="Normal">
              <internal_items />
            </InternalNormalItem>
          </MarkdownSegment>
          <MarkdownSegment
            trans_unit_id="115">
            <SegmentId>0a2b1da9-9bdf-4eae-91a9-793b63226b41</SegmentId>
            <InternalNormalItem
              internal_item_id="1"
              internal_item_parent_id="115"
              trans_unit_id="115-1"
              internal_item_type="Normal">
              <internal_items />
            </InternalNormalItem>
          </MarkdownSegment>
          <MarkdownSegment
            trans_unit_id="116">
            <SegmentId>413aa90e-9499-4933-997d-5acd37d37141</SegmentId>
            <InternalNormalItem
              internal_item_id="1"
              internal_item_parent_id="116"
              trans_unit_id="116-1"
              internal_item_type="Normal">
              <internal_items />
            </InternalNormalItem>
          </MarkdownSegment>
          <MarkdownSegment
            trans_unit_id="117">
            <SegmentId>7ae71da2-fcba-40ba-b287-6416f2dde263</SegmentId>
            <LinkItem
              internal_item_id="1"
              internal_item_parent_id="117"
              trans_unit_id="117-1"
              internal_item_type="Link">
              <internal_items />
              <internal_link_type>Inline</internal_link_type>
              <internal_link_text>This blog post</internal_link_text>
              <internal_link_url>http://azure.microsoft.com/blog/2015/08/17/containers-docker-windows-and-trends/</internal_link_url>
              <internal_link_title />
            </LinkItem>
            <InternalNormalItem
              internal_item_id="2"
              internal_item_parent_id="117"
              trans_unit_id="117-2"
              internal_item_type="Normal">
              <internal_items />
            </InternalNormalItem>
          </MarkdownSegment>
        </paragraph_segments>
      </MarkdownBlockBase>
      <MarkdownBlockBase
        xsi:type="MarkdownParagraphBlock"
        item_id="3293ae71-a8e3-4f2e-818d-163ba505a8d7"
        item_type="NormalParagraph"
        item_footer=""
        trans_unit_id="3293ae71-a8e3-4f2e-818d-163ba505a8d7">
        <Lines>
          <MarkdownLine>
            <LineId>6827d6da-adc1-4c07-a771-f3f97e45a485</LineId>
            <paragraph_segments>
              <MarkdownSegment
                trans_unit_id="118">
                <SegmentId>0165303b-d71e-4ea7-a417-3a2485e200f0</SegmentId>
                <InternalNormalItem
                  internal_item_id="1"
                  internal_item_parent_id="118"
                  trans_unit_id="118-1"
                  internal_item_type="Normal">
                  <internal_items />
                </InternalNormalItem>
              </MarkdownSegment>
            </paragraph_segments>
            <PrefixWSLength>0</PrefixWSLength>
            <SuffixWSLength>0</SuffixWSLength>
          </MarkdownLine>
        </Lines>
        <paragraph_segments>
          <MarkdownSegment
            trans_unit_id="118">
            <SegmentId>0165303b-d71e-4ea7-a417-3a2485e200f0</SegmentId>
            <InternalNormalItem
              internal_item_id="1"
              internal_item_parent_id="118"
              trans_unit_id="118-1"
              internal_item_type="Normal">
              <internal_items />
            </InternalNormalItem>
          </MarkdownSegment>
        </paragraph_segments>
      </MarkdownBlockBase>
      <MarkdownBlockBase
        xsi:type="MarkdownParagraphBlock"
        item_id="d19c861b-a405-4780-974a-4acad35e52ec"
        item_type="NormalParagraph"
        item_footer=""
        trans_unit_id="d19c861b-a405-4780-974a-4acad35e52ec">
        <Lines>
          <MarkdownLine>
            <LineId>6e7f371e-edea-4d09-9680-cc231e25fd52</LineId>
            <paragraph_segments>
              <MarkdownSegment
                trans_unit_id="119">
                <SegmentId>e2a58c16-ac78-4c18-9e01-cae3f01a8670</SegmentId>
                <MarkdownInternalBoldItem
                  internal_item_id="1"
                  internal_item_parent_id="119"
                  trans_unit_id="119-1"
                  internal_item_type="Bold">
                  <internal_items />
                  <internal_itatic_bold_item_type>Star</internal_itatic_bold_item_type>
                </MarkdownInternalBoldItem>
                <InternalNormalItem
                  internal_item_id="2"
                  internal_item_parent_id="119"
                  trans_unit_id="119-2"
                  internal_item_type="Normal">
                  <internal_items />
                </InternalNormalItem>
              </MarkdownSegment>
              <MarkdownSegment
                trans_unit_id="120">
                <SegmentId>9b9e1078-c5a7-42e8-ad61-0fec557be035</SegmentId>
                <InternalNormalItem
                  internal_item_id="1"
                  internal_item_parent_id="120"
                  trans_unit_id="120-1"
                  internal_item_type="Normal">
                  <internal_items />
                </InternalNormalItem>
              </MarkdownSegment>
            </paragraph_segments>
            <PrefixWSLength>0</PrefixWSLength>
            <SuffixWSLength>0</SuffixWSLength>
          </MarkdownLine>
        </Lines>
        <paragraph_segments>
          <MarkdownSegment
            trans_unit_id="119">
            <SegmentId>e2a58c16-ac78-4c18-9e01-cae3f01a8670</SegmentId>
            <MarkdownInternalBoldItem
              internal_item_id="1"
              internal_item_parent_id="119"
              trans_unit_id="119-1"
              internal_item_type="Bold">
              <internal_items />
              <internal_itatic_bold_item_type>Star</internal_itatic_bold_item_type>
            </MarkdownInternalBoldItem>
            <InternalNormalItem
              internal_item_id="2"
              internal_item_parent_id="119"
              trans_unit_id="119-2"
              internal_item_type="Normal">
              <internal_items />
            </InternalNormalItem>
          </MarkdownSegment>
          <MarkdownSegment
            trans_unit_id="120">
            <SegmentId>9b9e1078-c5a7-42e8-ad61-0fec557be035</SegmentId>
            <InternalNormalItem
              internal_item_id="1"
              internal_item_parent_id="120"
              trans_unit_id="120-1"
              internal_item_type="Normal">
              <internal_items />
            </InternalNormalItem>
          </MarkdownSegment>
        </paragraph_segments>
      </MarkdownBlockBase>
      <MarkdownBlockBase
        xsi:type="MarkdownParagraphBlock"
        item_id="82442a8b-60df-44ef-aa38-2e32bd3136bf"
        item_type="NormalParagraph"
        item_footer=""
        trans_unit_id="82442a8b-60df-44ef-aa38-2e32bd3136bf">
        <Lines>
          <MarkdownLine>
            <LineId>88250d9c-af57-4898-92b0-e51cf4b3352e</LineId>
            <paragraph_segments>
              <MarkdownSegment
                trans_unit_id="121">
                <SegmentId>469bdc4f-e422-4f09-95ae-4391a386e2e7</SegmentId>
                <MarkdownInternalBoldItem
                  internal_item_id="1"
                  internal_item_parent_id="121"
                  trans_unit_id="121-1"
                  internal_item_type="Bold">
                  <internal_items />
                  <internal_itatic_bold_item_type>Star</internal_itatic_bold_item_type>
                </MarkdownInternalBoldItem>
                <InternalNormalItem
                  internal_item_id="2"
                  internal_item_parent_id="121"
                  trans_unit_id="121-2"
                  internal_item_type="Normal">
                  <internal_items />
                </InternalNormalItem>
              </MarkdownSegment>
              <MarkdownSegment
                trans_unit_id="122">
                <SegmentId>2e75e2cc-2f81-4c62-9550-de58702b5c8b</SegmentId>
                <InternalNormalItem
                  internal_item_id="1"
                  internal_item_parent_id="122"
                  trans_unit_id="122-1"
                  internal_item_type="Normal">
                  <internal_items />
                </InternalNormalItem>
              </MarkdownSegment>
              <MarkdownSegment
                trans_unit_id="123">
                <SegmentId>74a91f40-b3fa-4e76-a709-9c784ef4000d</SegmentId>
                <InternalNormalItem
                  internal_item_id="1"
                  internal_item_parent_id="123"
                  trans_unit_id="123-1"
                  internal_item_type="Normal">
                  <internal_items />
                </InternalNormalItem>
              </MarkdownSegment>
              <MarkdownSegment
                trans_unit_id="124">
                <SegmentId>12b9d5e5-3d3b-4114-b2d3-b76f140cb1fb</SegmentId>
                <InternalNormalItem
                  internal_item_id="1"
                  internal_item_parent_id="124"
                  trans_unit_id="124-1"
                  internal_item_type="Normal">
                  <internal_items />
                </InternalNormalItem>
              </MarkdownSegment>
              <MarkdownSegment
                trans_unit_id="125">
                <SegmentId>8b2c5c58-7e9c-49f1-8571-09f00112b977</SegmentId>
                <InternalNormalItem
                  internal_item_id="1"
                  internal_item_parent_id="125"
                  trans_unit_id="125-1"
                  internal_item_type="Normal">
                  <internal_items />
                </InternalNormalItem>
              </MarkdownSegment>
              <MarkdownSegment
                trans_unit_id="126">
                <SegmentId>5a21fb19-4fc0-4e21-a705-caaaefd88236</SegmentId>
                <InternalNormalItem
                  internal_item_id="1"
                  internal_item_parent_id="126"
                  trans_unit_id="126-1"
                  internal_item_type="Normal">
                  <internal_items />
                </InternalNormalItem>
              </MarkdownSegment>
              <MarkdownSegment
                trans_unit_id="127">
                <SegmentId>978ca022-2d2d-4d8c-a81f-d840ba88d1f2</SegmentId>
                <InternalNormalItem
                  internal_item_id="1"
                  internal_item_parent_id="127"
                  trans_unit_id="127-1"
                  internal_item_type="Normal">
                  <internal_items />
                </InternalNormalItem>
              </MarkdownSegment>
            </paragraph_segments>
            <PrefixWSLength>0</PrefixWSLength>
            <SuffixWSLength>0</SuffixWSLength>
          </MarkdownLine>
        </Lines>
        <paragraph_segments>
          <MarkdownSegment
            trans_unit_id="121">
            <SegmentId>469bdc4f-e422-4f09-95ae-4391a386e2e7</SegmentId>
            <MarkdownInternalBoldItem
              internal_item_id="1"
              internal_item_parent_id="121"
              trans_unit_id="121-1"
              internal_item_type="Bold">
              <internal_items />
              <internal_itatic_bold_item_type>Star</internal_itatic_bold_item_type>
            </MarkdownInternalBoldItem>
            <InternalNormalItem
              internal_item_id="2"
              internal_item_parent_id="121"
              trans_unit_id="121-2"
              internal_item_type="Normal">
              <internal_items />
            </InternalNormalItem>
          </MarkdownSegment>
          <MarkdownSegment
            trans_unit_id="122">
            <SegmentId>2e75e2cc-2f81-4c62-9550-de58702b5c8b</SegmentId>
            <InternalNormalItem
              internal_item_id="1"
              internal_item_parent_id="122"
              trans_unit_id="122-1"
              internal_item_type="Normal">
              <internal_items />
            </InternalNormalItem>
          </MarkdownSegment>
          <MarkdownSegment
            trans_unit_id="123">
            <SegmentId>74a91f40-b3fa-4e76-a709-9c784ef4000d</SegmentId>
            <InternalNormalItem
              internal_item_id="1"
              internal_item_parent_id="123"
              trans_unit_id="123-1"
              internal_item_type="Normal">
              <internal_items />
            </InternalNormalItem>
          </MarkdownSegment>
          <MarkdownSegment
            trans_unit_id="124">
            <SegmentId>12b9d5e5-3d3b-4114-b2d3-b76f140cb1fb</SegmentId>
            <InternalNormalItem
              internal_item_id="1"
              internal_item_parent_id="124"
              trans_unit_id="124-1"
              internal_item_type="Normal">
              <internal_items />
            </InternalNormalItem>
          </MarkdownSegment>
          <MarkdownSegment
            trans_unit_id="125">
            <SegmentId>8b2c5c58-7e9c-49f1-8571-09f00112b977</SegmentId>
            <InternalNormalItem
              internal_item_id="1"
              internal_item_parent_id="125"
              trans_unit_id="125-1"
              internal_item_type="Normal">
              <internal_items />
            </InternalNormalItem>
          </MarkdownSegment>
          <MarkdownSegment
            trans_unit_id="126">
            <SegmentId>5a21fb19-4fc0-4e21-a705-caaaefd88236</SegmentId>
            <InternalNormalItem
              internal_item_id="1"
              internal_item_parent_id="126"
              trans_unit_id="126-1"
              internal_item_type="Normal">
              <internal_items />
            </InternalNormalItem>
          </MarkdownSegment>
          <MarkdownSegment
            trans_unit_id="127">
            <SegmentId>978ca022-2d2d-4d8c-a81f-d840ba88d1f2</SegmentId>
            <InternalNormalItem
              internal_item_id="1"
              internal_item_parent_id="127"
              trans_unit_id="127-1"
              internal_item_type="Normal">
              <internal_items />
            </InternalNormalItem>
          </MarkdownSegment>
        </paragraph_segments>
      </MarkdownBlockBase>
      <MarkdownBlockBase
        xsi:type="MarkdownParagraphBlock"
        item_id="1e201f85-2db3-4250-bce5-b4367315f25a"
        item_type="NormalParagraph"
        item_footer=""
        trans_unit_id="1e201f85-2db3-4250-bce5-b4367315f25a">
        <Lines>
          <MarkdownLine>
            <LineId>0dfaa1f9-d3cc-42a1-b20d-39562416f071</LineId>
            <paragraph_segments>
              <MarkdownSegment
                trans_unit_id="128">
                <SegmentId>18b2f634-945a-4a14-ac25-0ac376d087c3</SegmentId>
                <MarkdownInternalBoldItem
                  internal_item_id="1"
                  internal_item_parent_id="128"
                  trans_unit_id="128-1"
                  internal_item_type="Bold">
                  <internal_items />
                  <internal_itatic_bold_item_type>Star</internal_itatic_bold_item_type>
                </MarkdownInternalBoldItem>
                <InternalNormalItem
                  internal_item_id="2"
                  internal_item_parent_id="128"
                  trans_unit_id="128-2"
                  internal_item_type="Normal">
                  <internal_items />
                </InternalNormalItem>
              </MarkdownSegment>
            </paragraph_segments>
            <PrefixWSLength>0</PrefixWSLength>
            <SuffixWSLength>0</SuffixWSLength>
          </MarkdownLine>
        </Lines>
        <paragraph_segments>
          <MarkdownSegment
            trans_unit_id="128">
            <SegmentId>18b2f634-945a-4a14-ac25-0ac376d087c3</SegmentId>
            <MarkdownInternalBoldItem
              internal_item_id="1"
              internal_item_parent_id="128"
              trans_unit_id="128-1"
              internal_item_type="Bold">
              <internal_items />
              <internal_itatic_bold_item_type>Star</internal_itatic_bold_item_type>
            </MarkdownInternalBoldItem>
            <InternalNormalItem
              internal_item_id="2"
              internal_item_parent_id="128"
              trans_unit_id="128-2"
              internal_item_type="Normal">
              <internal_items />
            </InternalNormalItem>
          </MarkdownSegment>
        </paragraph_segments>
      </MarkdownBlockBase>
      <MarkdownBlockBase
        xsi:type="MarkdownParagraphBlock"
        item_id="3df41351-c6b4-4263-bcb4-07e9c27e5238"
        item_type="NormalParagraph"
        item_footer=""
        trans_unit_id="3df41351-c6b4-4263-bcb4-07e9c27e5238">
        <Lines>
          <MarkdownLine>
            <LineId>c78e7168-4f7e-4fc6-a224-470549d0db8d</LineId>
            <paragraph_segments>
              <MarkdownSegment
                trans_unit_id="129">
                <SegmentId>e6ce8912-4cc8-436a-82d4-b07e828d82d0</SegmentId>
                <MarkdownInternalBoldItem
                  internal_item_id="1"
                  internal_item_parent_id="129"
                  trans_unit_id="129-1"
                  internal_item_type="Bold">
                  <internal_items />
                  <internal_itatic_bold_item_type>Star</internal_itatic_bold_item_type>
                </MarkdownInternalBoldItem>
                <InternalNormalItem
                  internal_item_id="2"
                  internal_item_parent_id="129"
                  trans_unit_id="129-2"
                  internal_item_type="Normal">
                  <internal_items />
                </InternalNormalItem>
              </MarkdownSegment>
              <MarkdownSegment
                trans_unit_id="130">
                <SegmentId>ba570542-6b6b-4c5b-a3b0-7720587cc3eb</SegmentId>
                <InternalNormalItem
                  internal_item_id="1"
                  internal_item_parent_id="130"
                  trans_unit_id="130-1"
                  internal_item_type="Normal">
                  <internal_items />
                </InternalNormalItem>
              </MarkdownSegment>
              <MarkdownSegment
                trans_unit_id="131">
                <SegmentId>daa4ae02-9744-4f38-8927-eb9f64fd6487</SegmentId>
                <InternalNormalItem
                  internal_item_id="1"
                  internal_item_parent_id="131"
                  trans_unit_id="131-1"
                  internal_item_type="Normal">
                  <internal_items />
                </InternalNormalItem>
              </MarkdownSegment>
              <MarkdownSegment
                trans_unit_id="132">
                <SegmentId>ca345df0-76d3-4f48-82ff-7ba12b0875de</SegmentId>
                <InternalNormalItem
                  internal_item_id="1"
                  internal_item_parent_id="132"
                  trans_unit_id="132-1"
                  internal_item_type="Normal">
                  <internal_items />
                </InternalNormalItem>
              </MarkdownSegment>
            </paragraph_segments>
            <PrefixWSLength>0</PrefixWSLength>
            <SuffixWSLength>0</SuffixWSLength>
          </MarkdownLine>
        </Lines>
        <paragraph_segments>
          <MarkdownSegment
            trans_unit_id="129">
            <SegmentId>e6ce8912-4cc8-436a-82d4-b07e828d82d0</SegmentId>
            <MarkdownInternalBoldItem
              internal_item_id="1"
              internal_item_parent_id="129"
              trans_unit_id="129-1"
              internal_item_type="Bold">
              <internal_items />
              <internal_itatic_bold_item_type>Star</internal_itatic_bold_item_type>
            </MarkdownInternalBoldItem>
            <InternalNormalItem
              internal_item_id="2"
              internal_item_parent_id="129"
              trans_unit_id="129-2"
              internal_item_type="Normal">
              <internal_items />
            </InternalNormalItem>
          </MarkdownSegment>
          <MarkdownSegment
            trans_unit_id="130">
            <SegmentId>ba570542-6b6b-4c5b-a3b0-7720587cc3eb</SegmentId>
            <InternalNormalItem
              internal_item_id="1"
              internal_item_parent_id="130"
              trans_unit_id="130-1"
              internal_item_type="Normal">
              <internal_items />
            </InternalNormalItem>
          </MarkdownSegment>
          <MarkdownSegment
            trans_unit_id="131">
            <SegmentId>daa4ae02-9744-4f38-8927-eb9f64fd6487</SegmentId>
            <InternalNormalItem
              internal_item_id="1"
              internal_item_parent_id="131"
              trans_unit_id="131-1"
              internal_item_type="Normal">
              <internal_items />
            </InternalNormalItem>
          </MarkdownSegment>
          <MarkdownSegment
            trans_unit_id="132">
            <SegmentId>ca345df0-76d3-4f48-82ff-7ba12b0875de</SegmentId>
            <InternalNormalItem
              internal_item_id="1"
              internal_item_parent_id="132"
              trans_unit_id="132-1"
              internal_item_type="Normal">
              <internal_items />
            </InternalNormalItem>
          </MarkdownSegment>
        </paragraph_segments>
      </MarkdownBlockBase>
      <MarkdownBlockBase
        xsi:type="MarkdownParagraphBlock"
        item_id="3310300d-7b89-4a0f-b8f2-3c9372a42711"
        item_type="NormalParagraph"
        item_footer=""
        trans_unit_id="3310300d-7b89-4a0f-b8f2-3c9372a42711">
        <Lines>
          <MarkdownLine>
            <LineId>1a661752-025e-4b2b-9989-5db69c13da37</LineId>
            <paragraph_segments>
              <MarkdownSegment
                trans_unit_id="133">
                <SegmentId>9caccafb-66eb-4d48-aee3-3db4c01fff76</SegmentId>
                <MarkdownInternalBoldItem
                  internal_item_id="1"
                  internal_item_parent_id="133"
                  trans_unit_id="133-1"
                  internal_item_type="Bold">
                  <internal_items />
                  <internal_itatic_bold_item_type>Star</internal_itatic_bold_item_type>
                </MarkdownInternalBoldItem>
                <InternalNormalItem
                  internal_item_id="2"
                  internal_item_parent_id="133"
                  trans_unit_id="133-2"
                  internal_item_type="Normal">
                  <internal_items />
                </InternalNormalItem>
              </MarkdownSegment>
              <MarkdownSegment
                trans_unit_id="134">
                <SegmentId>dc899f87-027c-40dd-8743-fea9892da7c0</SegmentId>
                <InternalNormalItem
                  internal_item_id="1"
                  internal_item_parent_id="134"
                  trans_unit_id="134-1"
                  internal_item_type="Normal">
                  <internal_items />
                </InternalNormalItem>
              </MarkdownSegment>
              <MarkdownSegment
                trans_unit_id="135">
                <SegmentId>60504984-df5c-4c44-8280-e2fe5c234bd4</SegmentId>
                <InternalNormalItem
                  internal_item_id="1"
                  internal_item_parent_id="135"
                  trans_unit_id="135-1"
                  internal_item_type="Normal">
                  <internal_items />
                </InternalNormalItem>
              </MarkdownSegment>
            </paragraph_segments>
            <PrefixWSLength>0</PrefixWSLength>
            <SuffixWSLength>0</SuffixWSLength>
          </MarkdownLine>
        </Lines>
        <paragraph_segments>
          <MarkdownSegment
            trans_unit_id="133">
            <SegmentId>9caccafb-66eb-4d48-aee3-3db4c01fff76</SegmentId>
            <MarkdownInternalBoldItem
              internal_item_id="1"
              internal_item_parent_id="133"
              trans_unit_id="133-1"
              internal_item_type="Bold">
              <internal_items />
              <internal_itatic_bold_item_type>Star</internal_itatic_bold_item_type>
            </MarkdownInternalBoldItem>
            <InternalNormalItem
              internal_item_id="2"
              internal_item_parent_id="133"
              trans_unit_id="133-2"
              internal_item_type="Normal">
              <internal_items />
            </InternalNormalItem>
          </MarkdownSegment>
          <MarkdownSegment
            trans_unit_id="134">
            <SegmentId>dc899f87-027c-40dd-8743-fea9892da7c0</SegmentId>
            <InternalNormalItem
              internal_item_id="1"
              internal_item_parent_id="134"
              trans_unit_id="134-1"
              internal_item_type="Normal">
              <internal_items />
            </InternalNormalItem>
          </MarkdownSegment>
          <MarkdownSegment
            trans_unit_id="135">
            <SegmentId>60504984-df5c-4c44-8280-e2fe5c234bd4</SegmentId>
            <InternalNormalItem
              internal_item_id="1"
              internal_item_parent_id="135"
              trans_unit_id="135-1"
              internal_item_type="Normal">
              <internal_items />
            </InternalNormalItem>
          </MarkdownSegment>
        </paragraph_segments>
      </MarkdownBlockBase>
      <MarkdownBlockBase
        xsi:type="MarkdownParagraphBlock"
        item_id="82df1f44-7ab9-4001-85b4-64f11e6e173d"
        item_type="NormalParagraph"
        item_footer=""
        trans_unit_id="82df1f44-7ab9-4001-85b4-64f11e6e173d">
        <Lines>
          <MarkdownLine>
            <LineId>a58274ed-2562-4c1b-aed8-0d1e763ca74d</LineId>
            <paragraph_segments>
              <MarkdownSegment
                trans_unit_id="136">
                <SegmentId>4c37994b-9b8f-4605-9ff3-f9d5a57764f1</SegmentId>
                <MarkdownInternalBoldItem
                  internal_item_id="1"
                  internal_item_parent_id="136"
                  trans_unit_id="136-1"
                  internal_item_type="Bold">
                  <internal_items />
                  <internal_itatic_bold_item_type>Star</internal_itatic_bold_item_type>
                </MarkdownInternalBoldItem>
                <InternalNormalItem
                  internal_item_id="2"
                  internal_item_parent_id="136"
                  trans_unit_id="136-2"
                  internal_item_type="Normal">
                  <internal_items />
                </InternalNormalItem>
              </MarkdownSegment>
              <MarkdownSegment
                trans_unit_id="137">
                <SegmentId>48b31c7a-9d5b-477c-a7a5-d5877d3fd4c7</SegmentId>
                <InternalNormalItem
                  internal_item_id="1"
                  internal_item_parent_id="137"
                  trans_unit_id="137-1"
                  internal_item_type="Normal">
                  <internal_items />
                </InternalNormalItem>
              </MarkdownSegment>
            </paragraph_segments>
            <PrefixWSLength>0</PrefixWSLength>
            <SuffixWSLength>0</SuffixWSLength>
          </MarkdownLine>
        </Lines>
        <paragraph_segments>
          <MarkdownSegment
            trans_unit_id="136">
            <SegmentId>4c37994b-9b8f-4605-9ff3-f9d5a57764f1</SegmentId>
            <MarkdownInternalBoldItem
              internal_item_id="1"
              internal_item_parent_id="136"
              trans_unit_id="136-1"
              internal_item_type="Bold">
              <internal_items />
              <internal_itatic_bold_item_type>Star</internal_itatic_bold_item_type>
            </MarkdownInternalBoldItem>
            <InternalNormalItem
              internal_item_id="2"
              internal_item_parent_id="136"
              trans_unit_id="136-2"
              internal_item_type="Normal">
              <internal_items />
            </InternalNormalItem>
          </MarkdownSegment>
          <MarkdownSegment
            trans_unit_id="137">
            <SegmentId>48b31c7a-9d5b-477c-a7a5-d5877d3fd4c7</SegmentId>
            <InternalNormalItem
              internal_item_id="1"
              internal_item_parent_id="137"
              trans_unit_id="137-1"
              internal_item_type="Normal">
              <internal_items />
            </InternalNormalItem>
          </MarkdownSegment>
        </paragraph_segments>
      </MarkdownBlockBase>
      <MarkdownBlockBase
        xsi:type="MarkdownParagraphBlock"
        item_id="0976e351-4eae-45de-842c-136dca70e743"
        item_type="NormalParagraph"
        item_footer=""
        trans_unit_id="0976e351-4eae-45de-842c-136dca70e743">
        <Lines>
          <MarkdownLine>
            <LineId>8613217c-af20-4796-870d-cd26b11bf95f</LineId>
            <paragraph_segments>
              <MarkdownSegment
                trans_unit_id="138">
                <SegmentId>e6a7c0c2-00af-4182-9d37-7943ef61da90</SegmentId>
                <MarkdownInternalHtmlTag
                  internal_item_id="1"
                  internal_item_parent_id="138"
                  trans_unit_id="138-1"
                  internal_item_type="HtmlTag">
                  <internal_items />
                  <itemValue>&lt;center&gt;</itemValue>
                </MarkdownInternalHtmlTag>
                <ImageItem
                  internal_item_id="2"
                  internal_item_parent_id="138"
                  trans_unit_id="138-2"
                  internal_item_type="Image">
                  <internal_items />
                  <internal_Image_type>Inline</internal_Image_type>
                  <internal_link_text />
                  <internal_link_url>media/containerfund.png</internal_link_url>
                  <internal_link_title />
                </ImageItem>
                <MarkdownInternalHtmlTag
                  internal_item_id="3"
                  internal_item_parent_id="138"
                  trans_unit_id="138-3"
                  internal_item_type="HtmlTag">
                  <internal_items />
                  <itemValue>&lt;/center&gt;</itemValue>
                </MarkdownInternalHtmlTag>
              </MarkdownSegment>
            </paragraph_segments>
            <PrefixWSLength>0</PrefixWSLength>
            <SuffixWSLength>0</SuffixWSLength>
          </MarkdownLine>
        </Lines>
        <paragraph_segments>
          <MarkdownSegment
            trans_unit_id="138">
            <SegmentId>e6a7c0c2-00af-4182-9d37-7943ef61da90</SegmentId>
            <MarkdownInternalHtmlTag
              internal_item_id="1"
              internal_item_parent_id="138"
              trans_unit_id="138-1"
              internal_item_type="HtmlTag">
              <internal_items />
              <itemValue>&lt;center&gt;</itemValue>
            </MarkdownInternalHtmlTag>
            <ImageItem
              internal_item_id="2"
              internal_item_parent_id="138"
              trans_unit_id="138-2"
              internal_item_type="Image">
              <internal_items />
              <internal_Image_type>Inline</internal_Image_type>
              <internal_link_text />
              <internal_link_url>media/containerfund.png</internal_link_url>
              <internal_link_title />
            </ImageItem>
            <MarkdownInternalHtmlTag
              internal_item_id="3"
              internal_item_parent_id="138"
              trans_unit_id="138-3"
              internal_item_type="HtmlTag">
              <internal_items />
              <itemValue>&lt;/center&gt;</itemValue>
            </MarkdownInternalHtmlTag>
          </MarkdownSegment>
        </paragraph_segments>
      </MarkdownBlockBase>
      <MarkdownBlockBase
        xsi:type="MarkdownHeaderBlock"
        item_id="ae1490c7-f792-4264-82c1-38f3611df98b"
        item_type="Header"
        item_footer="footer_not_set"
        trans_unit_id="ae1490c7-f792-4264-82c1-38f3611df98b">
        <segment
          trans_unit_id="139">
          <SegmentId>75ca95af-e922-4666-9dab-1aac7ff18e9e</SegmentId>
          <InternalNormalItem
            internal_item_id="1"
            internal_item_parent_id="139"
            trans_unit_id="139-1"
            internal_item_type="Normal">
            <internal_items />
          </InternalNormalItem>
        </segment>
        <header_type>Star</header_type>
        <header_level>2</header_level>
      </MarkdownBlockBase>
      <MarkdownBlockBase
        xsi:type="MarkdownParagraphBlock"
        item_id="b5885784-ebaa-4b92-b98b-cb68d4ca6efb"
        item_type="NormalParagraph"
        item_footer=""
        trans_unit_id="b5885784-ebaa-4b92-b98b-cb68d4ca6efb">
        <Lines>
          <MarkdownLine>
            <LineId>fdd4ac0f-280c-435c-bef8-3b8ca9389409</LineId>
            <paragraph_segments>
              <MarkdownSegment
                trans_unit_id="140">
                <SegmentId>53f5f51b-c6ba-4287-93db-d2c9d7fdd8cb</SegmentId>
                <InternalNormalItem
                  internal_item_id="1"
                  internal_item_parent_id="140"
                  trans_unit_id="140-1"
                  internal_item_type="Normal">
                  <internal_items />
                </InternalNormalItem>
              </MarkdownSegment>
              <MarkdownSegment
                trans_unit_id="141">
                <SegmentId>2b5b2131-5b60-41dc-b66d-af1288d73991</SegmentId>
                <InternalNormalItem
                  internal_item_id="1"
                  internal_item_parent_id="141"
                  trans_unit_id="141-1"
                  internal_item_type="Normal">
                  <internal_items />
                </InternalNormalItem>
              </MarkdownSegment>
            </paragraph_segments>
            <PrefixWSLength>0</PrefixWSLength>
            <SuffixWSLength>0</SuffixWSLength>
          </MarkdownLine>
        </Lines>
        <paragraph_segments>
          <MarkdownSegment
            trans_unit_id="140">
            <SegmentId>53f5f51b-c6ba-4287-93db-d2c9d7fdd8cb</SegmentId>
            <InternalNormalItem
              internal_item_id="1"
              internal_item_parent_id="140"
              trans_unit_id="140-1"
              internal_item_type="Normal">
              <internal_items />
            </InternalNormalItem>
          </MarkdownSegment>
          <MarkdownSegment
            trans_unit_id="141">
            <SegmentId>2b5b2131-5b60-41dc-b66d-af1288d73991</SegmentId>
            <InternalNormalItem
              internal_item_id="1"
              internal_item_parent_id="141"
              trans_unit_id="141-1"
              internal_item_type="Normal">
              <internal_items />
            </InternalNormalItem>
          </MarkdownSegment>
        </paragraph_segments>
      </MarkdownBlockBase>
      <MarkdownBlockBase
        xsi:type="MarkdownParagraphBlock"
        item_id="452358ce-1465-4e27-81a3-a237b3402b34"
        item_type="NormalParagraph"
        item_footer=""
        trans_unit_id="452358ce-1465-4e27-81a3-a237b3402b34">
        <Lines>
          <MarkdownLine>
            <LineId>a39c73e8-d300-48db-988d-1b6482a18e94</LineId>
            <paragraph_segments>
              <MarkdownSegment
                trans_unit_id="142">
                <SegmentId>0aab45cd-a15f-4255-8590-2831d67f97e3</SegmentId>
                <InternalNormalItem
                  internal_item_id="1"
                  internal_item_parent_id="142"
                  trans_unit_id="142-1"
                  internal_item_type="Normal">
                  <internal_items />
                </InternalNormalItem>
              </MarkdownSegment>
              <MarkdownSegment
                trans_unit_id="143">
                <SegmentId>c0587bc2-5709-48e3-993c-47a940641526</SegmentId>
                <InternalNormalItem
                  internal_item_id="1"
                  internal_item_parent_id="143"
                  trans_unit_id="143-1"
                  internal_item_type="Normal">
                  <internal_items />
                </InternalNormalItem>
              </MarkdownSegment>
              <MarkdownSegment
                trans_unit_id="144">
                <SegmentId>2a47290a-e958-4195-a3aa-2c346b0a024a</SegmentId>
                <InternalNormalItem
                  internal_item_id="1"
                  internal_item_parent_id="144"
                  trans_unit_id="144-1"
                  internal_item_type="Normal">
                  <internal_items />
                </InternalNormalItem>
              </MarkdownSegment>
              <MarkdownSegment
                trans_unit_id="145">
                <SegmentId>b4fc76e7-784b-4f36-a4b5-02b0f102a3e6</SegmentId>
                <InternalNormalItem
                  internal_item_id="1"
                  internal_item_parent_id="145"
                  trans_unit_id="145-1"
                  internal_item_type="Normal">
                  <internal_items />
                </InternalNormalItem>
              </MarkdownSegment>
              <MarkdownSegment
                trans_unit_id="146">
                <SegmentId>19630a7e-dd94-44de-ac69-1731141f627c</SegmentId>
                <InternalNormalItem
                  internal_item_id="1"
                  internal_item_parent_id="146"
                  trans_unit_id="146-1"
                  internal_item_type="Normal">
                  <internal_items />
                </InternalNormalItem>
              </MarkdownSegment>
            </paragraph_segments>
            <PrefixWSLength>0</PrefixWSLength>
            <SuffixWSLength>0</SuffixWSLength>
          </MarkdownLine>
        </Lines>
        <paragraph_segments>
          <MarkdownSegment
            trans_unit_id="142">
            <SegmentId>0aab45cd-a15f-4255-8590-2831d67f97e3</SegmentId>
            <InternalNormalItem
              internal_item_id="1"
              internal_item_parent_id="142"
              trans_unit_id="142-1"
              internal_item_type="Normal">
              <internal_items />
            </InternalNormalItem>
          </MarkdownSegment>
          <MarkdownSegment
            trans_unit_id="143">
            <SegmentId>c0587bc2-5709-48e3-993c-47a940641526</SegmentId>
            <InternalNormalItem
              internal_item_id="1"
              internal_item_parent_id="143"
              trans_unit_id="143-1"
              internal_item_type="Normal">
              <internal_items />
            </InternalNormalItem>
          </MarkdownSegment>
          <MarkdownSegment
            trans_unit_id="144">
            <SegmentId>2a47290a-e958-4195-a3aa-2c346b0a024a</SegmentId>
            <InternalNormalItem
              internal_item_id="1"
              internal_item_parent_id="144"
              trans_unit_id="144-1"
              internal_item_type="Normal">
              <internal_items />
            </InternalNormalItem>
          </MarkdownSegment>
          <MarkdownSegment
            trans_unit_id="145">
            <SegmentId>b4fc76e7-784b-4f36-a4b5-02b0f102a3e6</SegmentId>
            <InternalNormalItem
              internal_item_id="1"
              internal_item_parent_id="145"
              trans_unit_id="145-1"
              internal_item_type="Normal">
              <internal_items />
            </InternalNormalItem>
          </MarkdownSegment>
          <MarkdownSegment
            trans_unit_id="146">
            <SegmentId>19630a7e-dd94-44de-ac69-1731141f627c</SegmentId>
            <InternalNormalItem
              internal_item_id="1"
              internal_item_parent_id="146"
              trans_unit_id="146-1"
              internal_item_type="Normal">
              <internal_items />
            </InternalNormalItem>
          </MarkdownSegment>
        </paragraph_segments>
      </MarkdownBlockBase>
      <MarkdownBlockBase
        xsi:type="MarkdownParagraphBlock"
        item_id="d40ee2a5-63aa-4ea6-9529-082adcbaa6a6"
        item_type="NormalParagraph"
        item_footer=""
        trans_unit_id="d40ee2a5-63aa-4ea6-9529-082adcbaa6a6">
        <Lines>
          <MarkdownLine>
            <LineId>757ceecc-b123-4e8e-a763-42a3a9624f33</LineId>
            <paragraph_segments>
              <MarkdownSegment
                trans_unit_id="147">
                <SegmentId>5e5354d8-4db0-4e46-b594-1cb03353b740</SegmentId>
                <InternalNormalItem
                  internal_item_id="1"
                  internal_item_parent_id="147"
                  trans_unit_id="147-1"
                  internal_item_type="Normal">
                  <internal_items />
                </InternalNormalItem>
              </MarkdownSegment>
              <MarkdownSegment
                trans_unit_id="148">
                <SegmentId>147ef039-0f2b-4d4d-b37a-dc3d6f4f2f0e</SegmentId>
                <InternalNormalItem
                  internal_item_id="1"
                  internal_item_parent_id="148"
                  trans_unit_id="148-1"
                  internal_item_type="Normal">
                  <internal_items />
                </InternalNormalItem>
              </MarkdownSegment>
              <MarkdownSegment
                trans_unit_id="149">
                <SegmentId>7b11a159-b661-430a-9789-04305ca6e3b6</SegmentId>
                <InternalNormalItem
                  internal_item_id="1"
                  internal_item_parent_id="149"
                  trans_unit_id="149-1"
                  internal_item_type="Normal">
                  <internal_items />
                </InternalNormalItem>
              </MarkdownSegment>
            </paragraph_segments>
            <PrefixWSLength>0</PrefixWSLength>
            <SuffixWSLength>0</SuffixWSLength>
          </MarkdownLine>
        </Lines>
        <paragraph_segments>
          <MarkdownSegment
            trans_unit_id="147">
            <SegmentId>5e5354d8-4db0-4e46-b594-1cb03353b740</SegmentId>
            <InternalNormalItem
              internal_item_id="1"
              internal_item_parent_id="147"
              trans_unit_id="147-1"
              internal_item_type="Normal">
              <internal_items />
            </InternalNormalItem>
          </MarkdownSegment>
          <MarkdownSegment
            trans_unit_id="148">
            <SegmentId>147ef039-0f2b-4d4d-b37a-dc3d6f4f2f0e</SegmentId>
            <InternalNormalItem
              internal_item_id="1"
              internal_item_parent_id="148"
              trans_unit_id="148-1"
              internal_item_type="Normal">
              <internal_items />
            </InternalNormalItem>
          </MarkdownSegment>
          <MarkdownSegment
            trans_unit_id="149">
            <SegmentId>7b11a159-b661-430a-9789-04305ca6e3b6</SegmentId>
            <InternalNormalItem
              internal_item_id="1"
              internal_item_parent_id="149"
              trans_unit_id="149-1"
              internal_item_type="Normal">
              <internal_items />
            </InternalNormalItem>
          </MarkdownSegment>
        </paragraph_segments>
      </MarkdownBlockBase>
      <MarkdownBlockBase
        xsi:type="MarkdownParagraphBlock"
        item_id="10d5e5e9-f3fb-4f46-8fc9-7fecfcd000eb"
        item_type="NormalParagraph"
        item_footer=""
        trans_unit_id="10d5e5e9-f3fb-4f46-8fc9-7fecfcd000eb">
        <Lines>
          <MarkdownLine>
            <LineId>34726054-8d4c-4ad3-9b6f-732173b9d935</LineId>
            <paragraph_segments>
              <MarkdownSegment
                trans_unit_id="150">
                <SegmentId>8b061d07-6fa3-41d1-8e64-d1d68e7f6035</SegmentId>
                <InternalNormalItem
                  internal_item_id="1"
                  internal_item_parent_id="150"
                  trans_unit_id="150-1"
                  internal_item_type="Normal">
                  <internal_items />
                </InternalNormalItem>
              </MarkdownSegment>
              <MarkdownSegment
                trans_unit_id="151">
                <SegmentId>81ba46a3-30f6-43f0-910e-d70acf62c155</SegmentId>
                <InternalNormalItem
                  internal_item_id="1"
                  internal_item_parent_id="151"
                  trans_unit_id="151-1"
                  internal_item_type="Normal">
                  <internal_items />
                </InternalNormalItem>
              </MarkdownSegment>
            </paragraph_segments>
            <PrefixWSLength>0</PrefixWSLength>
            <SuffixWSLength>0</SuffixWSLength>
          </MarkdownLine>
        </Lines>
        <paragraph_segments>
          <MarkdownSegment
            trans_unit_id="150">
            <SegmentId>8b061d07-6fa3-41d1-8e64-d1d68e7f6035</SegmentId>
            <InternalNormalItem
              internal_item_id="1"
              internal_item_parent_id="150"
              trans_unit_id="150-1"
              internal_item_type="Normal">
              <internal_items />
            </InternalNormalItem>
          </MarkdownSegment>
          <MarkdownSegment
            trans_unit_id="151">
            <SegmentId>81ba46a3-30f6-43f0-910e-d70acf62c155</SegmentId>
            <InternalNormalItem
              internal_item_id="1"
              internal_item_parent_id="151"
              trans_unit_id="151-1"
              internal_item_type="Normal">
              <internal_items />
            </InternalNormalItem>
          </MarkdownSegment>
        </paragraph_segments>
      </MarkdownBlockBase>
      <MarkdownBlockBase
        xsi:type="MarkdownParagraphBlock"
        item_id="74e32527-22b0-467a-8035-b966e286b711"
        item_type="NormalParagraph"
        item_footer=""
        trans_unit_id="74e32527-22b0-467a-8035-b966e286b711">
        <Lines>
          <MarkdownLine>
            <LineId>f02e8ea4-ccbb-49d6-9b82-70ee9abcb0c5</LineId>
            <paragraph_segments>
              <MarkdownSegment
                trans_unit_id="152">
                <SegmentId>f9d2ec98-1801-41ce-ad91-68e28a33016b</SegmentId>
                <InternalNormalItem
                  internal_item_id="1"
                  internal_item_parent_id="152"
                  trans_unit_id="152-1"
                  internal_item_type="Normal">
                  <internal_items />
                </InternalNormalItem>
              </MarkdownSegment>
            </paragraph_segments>
            <PrefixWSLength>0</PrefixWSLength>
            <SuffixWSLength>0</SuffixWSLength>
          </MarkdownLine>
        </Lines>
        <paragraph_segments>
          <MarkdownSegment
            trans_unit_id="152">
            <SegmentId>f9d2ec98-1801-41ce-ad91-68e28a33016b</SegmentId>
            <InternalNormalItem
              internal_item_id="1"
              internal_item_parent_id="152"
              trans_unit_id="152-1"
              internal_item_type="Normal">
              <internal_items />
            </InternalNormalItem>
          </MarkdownSegment>
        </paragraph_segments>
      </MarkdownBlockBase>
      <MarkdownBlockBase
        xsi:type="MarkdownHeaderBlock"
        item_id="55cf62db-721f-4ba1-a108-6bb30c62eef7"
        item_type="Header"
        item_footer="footer_not_set"
        trans_unit_id="55cf62db-721f-4ba1-a108-6bb30c62eef7">
        <segment
          trans_unit_id="153">
          <SegmentId>5723c14f-3b0c-46f9-8e8f-7b484c58a426</SegmentId>
          <InternalNormalItem
            internal_item_id="1"
            internal_item_parent_id="153"
            trans_unit_id="153-1"
            internal_item_type="Normal">
            <internal_items />
          </InternalNormalItem>
        </segment>
        <header_type>Star</header_type>
        <header_level>2</header_level>
      </MarkdownBlockBase>
      <MarkdownBlockBase
        xsi:type="MarkdownParagraphBlock"
        item_id="9cd02ffe-8ab0-40f7-bff6-e4c4fa384642"
        item_type="NormalParagraph"
        item_footer=""
        trans_unit_id="9cd02ffe-8ab0-40f7-bff6-e4c4fa384642">
        <Lines>
          <MarkdownLine>
            <LineId>a0406de2-d730-4979-b26a-506ca15e62c3</LineId>
            <paragraph_segments>
              <MarkdownSegment
                trans_unit_id="154">
                <SegmentId>d9fa1753-76da-40aa-8d6a-b2758ec55aa6</SegmentId>
                <InternalNormalItem
                  internal_item_id="1"
                  internal_item_parent_id="154"
                  trans_unit_id="154-1"
                  internal_item_type="Normal">
                  <internal_items />
                </InternalNormalItem>
              </MarkdownSegment>
              <MarkdownSegment
                trans_unit_id="155">
                <SegmentId>834ad2af-7798-4b51-821d-a2a51322f6ff</SegmentId>
                <InternalNormalItem
                  internal_item_id="1"
                  internal_item_parent_id="155"
                  trans_unit_id="155-1"
                  internal_item_type="Normal">
                  <internal_items />
                </InternalNormalItem>
              </MarkdownSegment>
              <MarkdownSegment
                trans_unit_id="156">
                <SegmentId>49b84fd7-f31a-4c7e-90ce-6d467105bbe4</SegmentId>
                <InternalNormalItem
                  internal_item_id="1"
                  internal_item_parent_id="156"
                  trans_unit_id="156-1"
                  internal_item_type="Normal">
                  <internal_items />
                </InternalNormalItem>
              </MarkdownSegment>
            </paragraph_segments>
            <PrefixWSLength>0</PrefixWSLength>
            <SuffixWSLength>0</SuffixWSLength>
          </MarkdownLine>
        </Lines>
        <paragraph_segments>
          <MarkdownSegment
            trans_unit_id="154">
            <SegmentId>d9fa1753-76da-40aa-8d6a-b2758ec55aa6</SegmentId>
            <InternalNormalItem
              internal_item_id="1"
              internal_item_parent_id="154"
              trans_unit_id="154-1"
              internal_item_type="Normal">
              <internal_items />
            </InternalNormalItem>
          </MarkdownSegment>
          <MarkdownSegment
            trans_unit_id="155">
            <SegmentId>834ad2af-7798-4b51-821d-a2a51322f6ff</SegmentId>
            <InternalNormalItem
              internal_item_id="1"
              internal_item_parent_id="155"
              trans_unit_id="155-1"
              internal_item_type="Normal">
              <internal_items />
            </InternalNormalItem>
          </MarkdownSegment>
          <MarkdownSegment
            trans_unit_id="156">
            <SegmentId>49b84fd7-f31a-4c7e-90ce-6d467105bbe4</SegmentId>
            <InternalNormalItem
              internal_item_id="1"
              internal_item_parent_id="156"
              trans_unit_id="156-1"
              internal_item_type="Normal">
              <internal_items />
            </InternalNormalItem>
          </MarkdownSegment>
        </paragraph_segments>
      </MarkdownBlockBase>
      <MarkdownBlockBase
        xsi:type="MarkdownParagraphBlock"
        item_id="02a4c0ce-fc63-4fba-bfc9-562763737d41"
        item_type="NormalParagraph"
        item_footer=""
        trans_unit_id="02a4c0ce-fc63-4fba-bfc9-562763737d41">
        <Lines>
          <MarkdownLine>
            <LineId>4f7a6c86-7a36-4845-ae92-d1005f9b08b7</LineId>
            <paragraph_segments>
              <MarkdownSegment
                trans_unit_id="157">
                <SegmentId>1868fc34-3fb7-4b4e-bb10-41e42bb3906d</SegmentId>
                <InternalNormalItem
                  internal_item_id="1"
                  internal_item_parent_id="157"
                  trans_unit_id="157-1"
                  internal_item_type="Normal">
                  <internal_items />
                </InternalNormalItem>
              </MarkdownSegment>
            </paragraph_segments>
            <PrefixWSLength>0</PrefixWSLength>
            <SuffixWSLength>0</SuffixWSLength>
          </MarkdownLine>
        </Lines>
        <paragraph_segments>
          <MarkdownSegment
            trans_unit_id="157">
            <SegmentId>1868fc34-3fb7-4b4e-bb10-41e42bb3906d</SegmentId>
            <InternalNormalItem
              internal_item_id="1"
              internal_item_parent_id="157"
              trans_unit_id="157-1"
              internal_item_type="Normal">
              <internal_items />
            </InternalNormalItem>
          </MarkdownSegment>
        </paragraph_segments>
      </MarkdownBlockBase>
      <MarkdownBlockBase
        xsi:type="MarkdownHeaderBlock"
        item_id="0f940395-df1e-458a-8f4b-5114e8531717"
        item_type="Header"
        item_footer="footer_not_set"
        trans_unit_id="0f940395-df1e-458a-8f4b-5114e8531717">
        <segment
          trans_unit_id="158">
          <SegmentId>8dfaca06-a2f9-4205-8213-91ab98dc994c</SegmentId>
          <InternalNormalItem
            internal_item_id="1"
            internal_item_parent_id="158"
            trans_unit_id="158-1"
            internal_item_type="Normal">
            <internal_items />
          </InternalNormalItem>
        </segment>
        <header_type>Star</header_type>
        <header_level>2</header_level>
      </MarkdownBlockBase>
      <MarkdownBlockBase
        xsi:type="MarkdownParagraphBlock"
        item_id="fd139a43-5346-417b-a0f2-a3437fe51f1a"
        item_type="NormalParagraph"
        item_footer="&#xA;"
        trans_unit_id="fd139a43-5346-417b-a0f2-a3437fe51f1a">
        <Lines>
          <MarkdownLine>
            <LineId>80e6ad0b-b927-460a-8fdd-dc2c8563dcfb</LineId>
            <paragraph_segments>
              <MarkdownSegment
                trans_unit_id="159">
                <SegmentId>738bf904-603d-487c-b5c2-94f7d48f8580</SegmentId>
                <InternalNormalItem
                  internal_item_id="1"
                  internal_item_parent_id="159"
                  trans_unit_id="159-1"
                  internal_item_type="Normal">
                  <internal_items />
                </InternalNormalItem>
              </MarkdownSegment>
            </paragraph_segments>
            <PrefixWSLength>0</PrefixWSLength>
            <SuffixWSLength>1</SuffixWSLength>
          </MarkdownLine>
          <MarkdownLine>
            <LineId>801fed46-ae07-4401-8584-775d7533476e</LineId>
            <paragraph_segments>
              <MarkdownSegment
                trans_unit_id="160">
                <SegmentId>63996bea-8a90-4b88-b3b3-993875997aec</SegmentId>
                <InternalNormalItem
                  internal_item_id="1"
                  internal_item_parent_id="160"
                  trans_unit_id="160-1"
                  internal_item_type="Normal">
                  <internal_items />
                </InternalNormalItem>
                <MarkdownInternalHtmlTag
                  internal_item_id="2"
                  internal_item_parent_id="160"
                  trans_unit_id="160-2"
                  internal_item_type="HtmlTag">
                  <internal_items />
                  <itemValue>&lt;/iframe&gt;</itemValue>
                </MarkdownInternalHtmlTag>
              </MarkdownSegment>
            </paragraph_segments>
            <PrefixWSLength>0</PrefixWSLength>
            <SuffixWSLength>0</SuffixWSLength>
          </MarkdownLine>
        </Lines>
        <paragraph_segments>
          <MarkdownSegment
            trans_unit_id="159">
            <SegmentId>738bf904-603d-487c-b5c2-94f7d48f8580</SegmentId>
            <InternalNormalItem
              internal_item_id="1"
              internal_item_parent_id="159"
              trans_unit_id="159-1"
              internal_item_type="Normal">
              <internal_items />
            </InternalNormalItem>
          </MarkdownSegment>
          <MarkdownSegment
            trans_unit_id="160">
            <SegmentId>63996bea-8a90-4b88-b3b3-993875997aec</SegmentId>
            <InternalNormalItem
              internal_item_id="1"
              internal_item_parent_id="160"
              trans_unit_id="160-1"
              internal_item_type="Normal">
              <internal_items />
            </InternalNormalItem>
            <MarkdownInternalHtmlTag
              internal_item_id="2"
              internal_item_parent_id="160"
              trans_unit_id="160-2"
              internal_item_type="HtmlTag">
              <internal_items />
              <itemValue>&lt;/iframe&gt;</itemValue>
            </MarkdownInternalHtmlTag>
          </MarkdownSegment>
        </paragraph_segments>
      </MarkdownBlockBase>
      <MarkdownBlockBase
        xsi:type="MarkdownHeaderBlock"
        item_id="0864f344-a7ac-40d7-ae68-3aa0b17a8cd8"
        item_type="Header"
        item_footer="footer_not_set"
        trans_unit_id="0864f344-a7ac-40d7-ae68-3aa0b17a8cd8">
        <segment
          trans_unit_id="161">
          <SegmentId>0eaaa9a8-d51d-42f5-b8e1-9b26a97120f0</SegmentId>
          <InternalNormalItem
            internal_item_id="1"
            internal_item_parent_id="161"
            trans_unit_id="161-1"
            internal_item_type="Normal">
            <internal_items />
          </InternalNormalItem>
        </segment>
        <header_type>Star</header_type>
        <header_level>2</header_level>
      </MarkdownBlockBase>
      <MarkdownBlockBase
        xsi:type="MarkdownParagraphBlock"
        item_id="89df772d-2802-4163-9a5b-e0e3a2e76685"
        item_type="NormalParagraph"
        item_footer=""
        trans_unit_id="89df772d-2802-4163-9a5b-e0e3a2e76685">
        <Lines>
          <MarkdownLine>
            <LineId>d9bfd0b6-789e-4efa-82e6-f10e7e040474</LineId>
            <paragraph_segments>
              <MarkdownSegment
                trans_unit_id="162">
                <SegmentId>9da329ad-826f-48ec-aaca-4dca2b741be7</SegmentId>
                <LinkItem
                  internal_item_id="1"
                  internal_item_parent_id="162"
                  trans_unit_id="162-1"
                  internal_item_type="Link">
                  <internal_items />
                  <internal_link_type>Inline</internal_link_type>
                  <internal_link_text>Get started with Windows Server Containers in Windows Azure</internal_link_text>
                  <internal_link_url>../quick_start/azure_setup.md</internal_link_url>
                  <internal_link_title />
                </LinkItem>
              </MarkdownSegment>
            </paragraph_segments>
            <PrefixWSLength>0</PrefixWSLength>
            <SuffixWSLength>2</SuffixWSLength>
          </MarkdownLine>
          <MarkdownLine>
            <LineId>75d25e02-13d2-447a-92e0-322e82ab2332</LineId>
            <paragraph_segments>
              <MarkdownSegment
                trans_unit_id="163">
                <SegmentId>9ef4905a-09e9-48a6-9908-d3ea5dc20015</SegmentId>
                <LinkItem
                  internal_item_id="1"
                  internal_item_parent_id="163"
                  trans_unit_id="163-1"
                  internal_item_type="Link">
                  <internal_items />
                  <internal_link_type>Inline</internal_link_type>
                  <internal_link_text>Get started with Windows Server Containers Locally</internal_link_text>
                  <internal_link_url>../quick_start/container_setup.md</internal_link_url>
                  <internal_link_title />
                </LinkItem>
              </MarkdownSegment>
            </paragraph_segments>
            <PrefixWSLength>0</PrefixWSLength>
            <SuffixWSLength>0</SuffixWSLength>
          </MarkdownLine>
        </Lines>
        <paragraph_segments>
          <MarkdownSegment
            trans_unit_id="162">
            <SegmentId>9da329ad-826f-48ec-aaca-4dca2b741be7</SegmentId>
            <LinkItem
              internal_item_id="1"
              internal_item_parent_id="162"
              trans_unit_id="162-1"
              internal_item_type="Link">
              <internal_items />
              <internal_link_type>Inline</internal_link_type>
              <internal_link_text>Get started with Windows Server Containers in Windows Azure</internal_link_text>
              <internal_link_url>../quick_start/azure_setup.md</internal_link_url>
              <internal_link_title />
            </LinkItem>
          </MarkdownSegment>
          <MarkdownSegment
            trans_unit_id="163">
            <SegmentId>9ef4905a-09e9-48a6-9908-d3ea5dc20015</SegmentId>
            <LinkItem
              internal_item_id="1"
              internal_item_parent_id="163"
              trans_unit_id="163-1"
              internal_item_type="Link">
              <internal_items />
              <internal_link_type>Inline</internal_link_type>
              <internal_link_text>Get started with Windows Server Containers Locally</internal_link_text>
              <internal_link_url>../quick_start/container_setup.md</internal_link_url>
              <internal_link_title />
            </LinkItem>
          </MarkdownSegment>
        </paragraph_segments>
      </MarkdownBlockBase>
      <MarkdownBlockBase
        xsi:type="MarkdownHorizonalRuleBlock"
        item_id="edcff392-9f1d-49b3-b4d7-7e63a0f8d977"
        item_type="HorizontalRule"
        item_footer="footer_not_set"
        trans_unit_id="edcff392-9f1d-49b3-b4d7-7e63a0f8d977">
        <horizonal_rule>-------------------</horizonal_rule>
      </MarkdownBlockBase>
      <MarkdownBlockBase
        xsi:type="MarkdownParagraphBlock"
        item_id="72a4de8b-4758-4122-ab0a-bb4c4acb538b"
        item_type="NormalParagraph"
        item_footer="&#xA;&#xA;"
        trans_unit_id="72a4de8b-4758-4122-ab0a-bb4c4acb538b">
        <Lines>
          <MarkdownLine>
            <LineId>924f31f8-54c4-46de-95fb-6e1d6ed061cd</LineId>
            <paragraph_segments>
              <MarkdownSegment
                trans_unit_id="164">
                <SegmentId>93bf20b2-4b02-4776-9feb-d18d7ce4d92b</SegmentId>
                <LinkItem
                  internal_item_id="1"
                  internal_item_parent_id="164"
                  trans_unit_id="164-1"
                  internal_item_type="Link">
                  <internal_items />
                  <internal_link_type>Inline</internal_link_type>
                  <internal_link_text>Back to Container Home</internal_link_text>
                  <internal_link_url>../containers_welcome.md</internal_link_url>
                  <internal_link_title />
                </LinkItem>
              </MarkdownSegment>
            </paragraph_segments>
            <PrefixWSLength>0</PrefixWSLength>
            <SuffixWSLength>0</SuffixWSLength>
          </MarkdownLine>
        </Lines>
        <paragraph_segments>
          <MarkdownSegment
            trans_unit_id="164">
            <SegmentId>93bf20b2-4b02-4776-9feb-d18d7ce4d92b</SegmentId>
            <LinkItem
              internal_item_id="1"
              internal_item_parent_id="164"
              trans_unit_id="164-1"
              internal_item_type="Link">
              <internal_items />
              <internal_link_type>Inline</internal_link_type>
              <internal_link_text>Back to Container Home</internal_link_text>
              <internal_link_url>../containers_welcome.md</internal_link_url>
              <internal_link_title />
            </LinkItem>
          </MarkdownSegment>
        </paragraph_segments>
      </MarkdownBlockBase>
    </ArrayOfMarkdownBlockBase>
  </block_element>
  <references>
    <ArrayOfMarkdownLinkedReference xmlns:xsd="http://www.w3.org/2001/XMLSchema" xmlns:xsi="http://www.w3.org/2001/XMLSchema-instance" />
  </references>
</markdown_skeleton_root>