<markdown_skeleton_root>
  <block_element>
    <ArrayOfMarkdownBlockBase xmlns:xsd="http://www.w3.org/2001/XMLSchema" xmlns:xsi="http://www.w3.org/2001/XMLSchema-instance">
      <MarkdownBlockBase
        xsi:type="MarkdownHeaderBlock"
        item_id="0070d99d-65bb-4af4-9c7f-e7f150cd6ae6"
        item_type="Header"
        item_footer="footer_not_set"
        trans_unit_id="0070d99d-65bb-4af4-9c7f-e7f150cd6ae6">
        <segment
          trans_unit_id="101">
          <SegmentId>687b79a6-f940-4974-9eeb-eb5191c54c10</SegmentId>
          <InternalNormalItem
            internal_item_id="1"
            internal_item_parent_id="101"
            trans_unit_id="101-1"
            internal_item_type="Normal">
            <internal_items />
          </InternalNormalItem>
        </segment>
        <header_type>Star</header_type>
        <header_level>2</header_level>
      </MarkdownBlockBase>
      <MarkdownBlockBase
        xsi:type="MarkdownListBlock"
        item_id="6d1bdc05-1d4b-4fe8-91aa-a4a4aef8b788"
        item_type="List"
        item_footer="&#xA;"
        trans_unit_id="6d1bdc05-1d4b-4fe8-91aa-a4a4aef8b788">
        <inner_list_items>
          <ListItem>
            <MarkdownParagraphBlock
              item_id="7c888e15-a66d-4351-8600-a8c01a2d34f9"
              item_type="NormalParagraph"
              item_footer="footer_not_set"
              trans_unit_id="7c888e15-a66d-4351-8600-a8c01a2d34f9">
              <Lines>
                <MarkdownLine>
                  <LineId>0b96ab0d-c4f8-413a-bb19-d5e89f46cbf3</LineId>
                  <paragraph_segments>
                    <MarkdownSegment
                      trans_unit_id="102">
                      <SegmentId>2e569cc6-1184-4992-a90f-0b98bc8f80c7</SegmentId>
                      <InternalNormalItem
                        internal_item_id="1"
                        internal_item_parent_id="102"
                        trans_unit_id="102-1"
                        internal_item_type="Normal">
                        <internal_items />
                      </InternalNormalItem>
                    </MarkdownSegment>
                  </paragraph_segments>
                  <PrefixWSLength>1</PrefixWSLength>
                  <SuffixWSLength>1</SuffixWSLength>
                </MarkdownLine>
                <MarkdownLine>
                  <LineId>25ba23af-63a1-40f0-919e-e64abf4fc56b</LineId>
                  <paragraph_segments>
                    <MarkdownSegment
                      trans_unit_id="103">
                      <SegmentId>095ead5e-a411-4fd0-906d-684eeb1c37ed</SegmentId>
                      <InternalNormalItem
                        internal_item_id="1"
                        internal_item_parent_id="103"
                        trans_unit_id="103-1"
                        internal_item_type="Normal">
                        <internal_items />
                      </InternalNormalItem>
                    </MarkdownSegment>
                  </paragraph_segments>
                  <PrefixWSLength>0</PrefixWSLength>
                  <SuffixWSLength>0</SuffixWSLength>
                </MarkdownLine>
              </Lines>
              <paragraph_segments>
                <MarkdownSegment
                  trans_unit_id="102">
                  <SegmentId>2e569cc6-1184-4992-a90f-0b98bc8f80c7</SegmentId>
                  <InternalNormalItem
                    internal_item_id="1"
                    internal_item_parent_id="102"
                    trans_unit_id="102-1"
                    internal_item_type="Normal">
                    <internal_items />
                  </InternalNormalItem>
                </MarkdownSegment>
                <MarkdownSegment
                  trans_unit_id="103">
                  <SegmentId>095ead5e-a411-4fd0-906d-684eeb1c37ed</SegmentId>
                  <InternalNormalItem
                    internal_item_id="1"
                    internal_item_parent_id="103"
                    trans_unit_id="103-1"
                    internal_item_type="Normal">
                    <internal_items />
                  </InternalNormalItem>
                </MarkdownSegment>
              </paragraph_segments>
            </MarkdownParagraphBlock>
            <Identifier>*</Identifier>
            <IndentsLength>
              <int>0</int>
              <int>0</int>
            </IndentsLength>
          </ListItem>
        </inner_list_items>
        <ListType>Charactor</ListType>
      </MarkdownBlockBase>
    </ArrayOfMarkdownBlockBase>
  </block_element>
  <references>
    <ArrayOfMarkdownLinkedReference xmlns:xsd="http://www.w3.org/2001/XMLSchema" xmlns:xsi="http://www.w3.org/2001/XMLSchema-instance" />
  </references>
</markdown_skeleton_root>