<markdown_skeleton_root>
  <block_element>
    <ArrayOfMarkdownBlockBase xmlns:xsd="http://www.w3.org/2001/XMLSchema" xmlns:xsi="http://www.w3.org/2001/XMLSchema-instance">
      <MarkdownBlockBase
        xsi:type="MarkdownHeaderBlock"
        item_id="fd3b1386-0cd1-4708-b748-333b0ae188fc"
        item_type="Header"
        item_footer="footer_not_set"
        trans_unit_id="fd3b1386-0cd1-4708-b748-333b0ae188fc">
        <segment
          trans_unit_id="101">
          <SegmentId>20820fed-c663-4b86-9939-580d9c58e789</SegmentId>
          <InternalNormalItem
            internal_item_id="1"
            internal_item_parent_id="101"
            trans_unit_id="101-1"
            internal_item_type="Normal">
            <internal_items />
          </InternalNormalItem>
        </segment>
        <header_type>Star</header_type>
        <header_level>2</header_level>
      </MarkdownBlockBase>
      <MarkdownBlockBase
        xsi:type="MarkdownListBlock"
        item_id="6ecbdf5d-fe1b-44d9-aaf5-6e7782ce5ef4"
        item_type="List"
        item_footer=""
        trans_unit_id="6ecbdf5d-fe1b-44d9-aaf5-6e7782ce5ef4">
        <inner_list_items>
          <ListItem>
            <MarkdownParagraphBlock
              item_id="57550e44-ce88-4d99-8c5c-48d93fd3c645"
              item_type="NormalParagraph"
              item_footer="footer_not_set"
              trans_unit_id="57550e44-ce88-4d99-8c5c-48d93fd3c645">
              <Lines>
                <MarkdownLine>
                  <LineId>1aec064e-7854-43ba-a6e0-b1d7a56a3929</LineId>
                  <paragraph_segments>
                    <MarkdownSegment
                      trans_unit_id="102">
                      <SegmentId>aeeb64c3-3bcd-4663-99a9-e58a67f58283</SegmentId>
                      <InternalNormalItem
                        internal_item_id="1"
                        internal_item_parent_id="102"
                        trans_unit_id="102-1"
                        internal_item_type="Normal">
                        <internal_items />
                      </InternalNormalItem>
                    </MarkdownSegment>
                  </paragraph_segments>
                  <PrefixWSLength>1</PrefixWSLength>
                  <SuffixWSLength>1</SuffixWSLength>
                </MarkdownLine>
                <MarkdownLine>
                  <LineId>5d69f194-e777-470e-bc66-9e574a2f6893</LineId>
                  <paragraph_segments>
                    <MarkdownSegment
                      trans_unit_id="103">
                      <SegmentId>9d91e92c-bdb1-4eec-9ce9-15d3c3f16d93</SegmentId>
                      <InternalNormalItem
                        internal_item_id="1"
                        internal_item_parent_id="103"
                        trans_unit_id="103-1"
                        internal_item_type="Normal">
                        <internal_items />
                      </InternalNormalItem>
                    </MarkdownSegment>
                  </paragraph_segments>
                  <PrefixWSLength>0</PrefixWSLength>
                  <SuffixWSLength>0</SuffixWSLength>
                </MarkdownLine>
              </Lines>
              <paragraph_segments>
                <MarkdownSegment
                  trans_unit_id="102">
                  <SegmentId>aeeb64c3-3bcd-4663-99a9-e58a67f58283</SegmentId>
                  <InternalNormalItem
                    internal_item_id="1"
                    internal_item_parent_id="102"
                    trans_unit_id="102-1"
                    internal_item_type="Normal">
                    <internal_items />
                  </InternalNormalItem>
                </MarkdownSegment>
                <MarkdownSegment
                  trans_unit_id="103">
                  <SegmentId>9d91e92c-bdb1-4eec-9ce9-15d3c3f16d93</SegmentId>
                  <InternalNormalItem
                    internal_item_id="1"
                    internal_item_parent_id="103"
                    trans_unit_id="103-1"
                    internal_item_type="Normal">
                    <internal_items />
                  </InternalNormalItem>
                </MarkdownSegment>
              </paragraph_segments>
            </MarkdownParagraphBlock>
            <Identifier>*</Identifier>
            <IndentsLength>
              <int>0</int>
              <int>0</int>
            </IndentsLength>
          </ListItem>
        </inner_list_items>
        <ListType>Charactor</ListType>
      </MarkdownBlockBase>
      <MarkdownBlockBase
        xsi:type="MarkdownParagraphBlock"
        item_id="a5f88a2a-d8c6-4175-a986-36cfead56411"
        item_type="NormalParagraph"
        item_footer="&#xA;"
        trans_unit_id="a5f88a2a-d8c6-4175-a986-36cfead56411">
        <Lines>
          <MarkdownLine>
            <LineId>c5dc7067-48d7-4d44-9b7b-94367b583fae</LineId>
            <paragraph_segments>
              <MarkdownSegment
                trans_unit_id="104">
                <SegmentId>1b37ff16-a344-4795-8c29-67f3e27acbff</SegmentId>
                <InternalNormalItem
                  internal_item_id="1"
                  internal_item_parent_id="104"
                  trans_unit_id="104-1"
                  internal_item_type="Normal">
                  <internal_items />
                </InternalNormalItem>
              </MarkdownSegment>
            </paragraph_segments>
            <PrefixWSLength>0</PrefixWSLength>
            <SuffixWSLength>0</SuffixWSLength>
          </MarkdownLine>
        </Lines>
        <paragraph_segments>
          <MarkdownSegment
            trans_unit_id="104">
            <SegmentId>1b37ff16-a344-4795-8c29-67f3e27acbff</SegmentId>
            <InternalNormalItem
              internal_item_id="1"
              internal_item_parent_id="104"
              trans_unit_id="104-1"
              internal_item_type="Normal">
              <internal_items />
            </InternalNormalItem>
          </MarkdownSegment>
        </paragraph_segments>
      </MarkdownBlockBase>
    </ArrayOfMarkdownBlockBase>
  </block_element>
  <references>
    <ArrayOfMarkdownLinkedReference xmlns:xsd="http://www.w3.org/2001/XMLSchema" xmlns:xsi="http://www.w3.org/2001/XMLSchema-instance" />
  </references>
</markdown_skeleton_root>