<markdown_skeleton_root>
  <block_element>
    <ArrayOfMarkdownBlockBase xmlns:xsd="http://www.w3.org/2001/XMLSchema" xmlns:xsi="http://www.w3.org/2001/XMLSchema-instance">
      <MarkdownBlockBase
        xsi:type="MarkdownHeaderBlock"
        item_id="e562adc7-65ac-41b9-9893-6a20365a333a"
        item_type="Header"
        item_footer="footer_not_set"
        trans_unit_id="e562adc7-65ac-41b9-9893-6a20365a333a">
        <segment
          trans_unit_id="101">
          <SegmentId>515fe742-2830-444f-92c4-5b5ce510d1c6</SegmentId>
          <InternalNormalItem
            internal_item_id="1"
            internal_item_parent_id="101"
            trans_unit_id="101-1"
            internal_item_type="Normal">
            <internal_items />
          </InternalNormalItem>
        </segment>
        <header_type>Star</header_type>
        <header_level>2</header_level>
      </MarkdownBlockBase>
      <MarkdownBlockBase
        xsi:type="MarkdownListBlock"
        item_id="9973b52e-890a-4844-9b9a-80b2b8d05caf"
        item_type="List"
        item_footer="&#xA;"
        trans_unit_id="9973b52e-890a-4844-9b9a-80b2b8d05caf">
        <inner_list_items>
          <ListItem>
            <MarkdownParagraphBlock
              item_id="1b0936d8-bd9f-4fd6-8dfd-1b36b5893a34"
              item_type="NormalParagraph"
              item_footer="footer_not_set"
              trans_unit_id="1b0936d8-bd9f-4fd6-8dfd-1b36b5893a34">
              <Lines>
                <MarkdownLine>
                  <LineId>8e5d23c1-9c8f-4b1f-8d39-5743c5b084fd</LineId>
                  <paragraph_segments>
                    <MarkdownSegment
                      trans_unit_id="102">
                      <SegmentId>875c2161-8263-45d8-b87e-55b7b761af7a</SegmentId>
                      <InternalNormalItem
                        internal_item_id="1"
                        internal_item_parent_id="102"
                        trans_unit_id="102-1"
                        internal_item_type="Normal">
                        <internal_items />
                      </InternalNormalItem>
                    </MarkdownSegment>
                  </paragraph_segments>
                  <PrefixWSLength>1</PrefixWSLength>
                  <SuffixWSLength>1</SuffixWSLength>
                </MarkdownLine>
                <MarkdownLine>
                  <LineId>1f1584fd-8ebb-4311-8396-1a7699e7a894</LineId>
                  <paragraph_segments>
                    <MarkdownSegment
                      trans_unit_id="103">
                      <SegmentId>2348302e-fc8a-4d13-be6d-a7f0cf894215</SegmentId>
                      <InternalNormalItem
                        internal_item_id="1"
                        internal_item_parent_id="103"
                        trans_unit_id="103-1"
                        internal_item_type="Normal">
                        <internal_items />
                      </InternalNormalItem>
                    </MarkdownSegment>
                  </paragraph_segments>
                  <PrefixWSLength>0</PrefixWSLength>
                  <SuffixWSLength>0</SuffixWSLength>
                </MarkdownLine>
              </Lines>
              <paragraph_segments>
                <MarkdownSegment
                  trans_unit_id="102">
                  <SegmentId>875c2161-8263-45d8-b87e-55b7b761af7a</SegmentId>
                  <InternalNormalItem
                    internal_item_id="1"
                    internal_item_parent_id="102"
                    trans_unit_id="102-1"
                    internal_item_type="Normal">
                    <internal_items />
                  </InternalNormalItem>
                </MarkdownSegment>
                <MarkdownSegment
                  trans_unit_id="103">
                  <SegmentId>2348302e-fc8a-4d13-be6d-a7f0cf894215</SegmentId>
                  <InternalNormalItem
                    internal_item_id="1"
                    internal_item_parent_id="103"
                    trans_unit_id="103-1"
                    internal_item_type="Normal">
                    <internal_items />
                  </InternalNormalItem>
                </MarkdownSegment>
              </paragraph_segments>
            </MarkdownParagraphBlock>
            <Identifier>*</Identifier>
            <IndentsLength>
              <int>0</int>
              <int>0</int>
            </IndentsLength>
          </ListItem>
        </inner_list_items>
        <ListType>Charactor</ListType>
      </MarkdownBlockBase>
    </ArrayOfMarkdownBlockBase>
  </block_element>
  <references>
    <ArrayOfMarkdownLinkedReference xmlns:xsd="http://www.w3.org/2001/XMLSchema" xmlns:xsi="http://www.w3.org/2001/XMLSchema-instance" />
  </references>
</markdown_skeleton_root>