<markdown_skeleton_root>
  <block_element>
    <ArrayOfMarkdownBlockBase xmlns:xsd="http://www.w3.org/2001/XMLSchema" xmlns:xsi="http://www.w3.org/2001/XMLSchema-instance">
      <MarkdownBlockBase
        xsi:type="MarkdownHeaderBlock"
        item_id="18592bf1-2097-43aa-a88d-95747921eed4"
        item_type="Header"
        item_footer="footer_not_set"
        trans_unit_id="18592bf1-2097-43aa-a88d-95747921eed4">
        <segment
          trans_unit_id="101">
          <SegmentId>1f96e694-44ab-4be5-9724-5b62b9dd7e1a</SegmentId>
          <InternalNormalItem
            internal_item_id="1"
            internal_item_parent_id="101"
            trans_unit_id="101-1"
            internal_item_type="Normal">
            <internal_items />
          </InternalNormalItem>
        </segment>
        <header_type>Star</header_type>
        <header_level>2</header_level>
      </MarkdownBlockBase>
      <MarkdownBlockBase
        xsi:type="MarkdownListBlock"
        item_id="8d1a5d8d-2f83-40f5-8d27-03aaea0ab720"
        item_type="List"
        item_footer="&#xA;"
        trans_unit_id="8d1a5d8d-2f83-40f5-8d27-03aaea0ab720">
        <inner_list_items>
          <ListItem>
            <MarkdownParagraphBlock
              item_id="1bff91f2-e268-4700-973b-ca45aa83d6cb"
              item_type="NormalParagraph"
              item_footer="footer_not_set"
              trans_unit_id="1bff91f2-e268-4700-973b-ca45aa83d6cb">
              <Lines>
                <MarkdownLine>
                  <LineId>92a5d40a-d360-4c0e-ae8f-845843555489</LineId>
                  <paragraph_segments>
                    <MarkdownSegment
                      trans_unit_id="102">
                      <SegmentId>cef5501d-7c28-4648-bdd2-dd40fde83f84</SegmentId>
                      <InternalNormalItem
                        internal_item_id="1"
                        internal_item_parent_id="102"
                        trans_unit_id="102-1"
                        internal_item_type="Normal">
                        <internal_items />
                      </InternalNormalItem>
                    </MarkdownSegment>
                  </paragraph_segments>
                  <PrefixWSLength>1</PrefixWSLength>
                  <SuffixWSLength>1</SuffixWSLength>
                </MarkdownLine>
                <MarkdownLine>
                  <LineId>c16a5b15-c6dd-4ede-b310-8a9423658458</LineId>
                  <paragraph_segments>
                    <MarkdownSegment
                      trans_unit_id="103">
                      <SegmentId>39b8b937-4889-4123-9c5b-a12fe819ef9e</SegmentId>
                      <InternalNormalItem
                        internal_item_id="1"
                        internal_item_parent_id="103"
                        trans_unit_id="103-1"
                        internal_item_type="Normal">
                        <internal_items />
                      </InternalNormalItem>
                    </MarkdownSegment>
                  </paragraph_segments>
                  <PrefixWSLength>0</PrefixWSLength>
                  <SuffixWSLength>0</SuffixWSLength>
                </MarkdownLine>
              </Lines>
              <paragraph_segments>
                <MarkdownSegment
                  trans_unit_id="102">
                  <SegmentId>cef5501d-7c28-4648-bdd2-dd40fde83f84</SegmentId>
                  <InternalNormalItem
                    internal_item_id="1"
                    internal_item_parent_id="102"
                    trans_unit_id="102-1"
                    internal_item_type="Normal">
                    <internal_items />
                  </InternalNormalItem>
                </MarkdownSegment>
                <MarkdownSegment
                  trans_unit_id="103">
                  <SegmentId>39b8b937-4889-4123-9c5b-a12fe819ef9e</SegmentId>
                  <InternalNormalItem
                    internal_item_id="1"
                    internal_item_parent_id="103"
                    trans_unit_id="103-1"
                    internal_item_type="Normal">
                    <internal_items />
                  </InternalNormalItem>
                </MarkdownSegment>
              </paragraph_segments>
            </MarkdownParagraphBlock>
            <Identifier>*</Identifier>
            <IndentsLength>
              <int>0</int>
              <int>0</int>
            </IndentsLength>
          </ListItem>
        </inner_list_items>
        <ListType>Charactor</ListType>
      </MarkdownBlockBase>
    </ArrayOfMarkdownBlockBase>
  </block_element>
  <references>
    <ArrayOfMarkdownLinkedReference xmlns:xsd="http://www.w3.org/2001/XMLSchema" xmlns:xsi="http://www.w3.org/2001/XMLSchema-instance" />
  </references>
</markdown_skeleton_root>