<markdown_skeleton_root>
  <block_element>
    <ArrayOfMarkdownBlockBase xmlns:xsd="http://www.w3.org/2001/XMLSchema" xmlns:xsi="http://www.w3.org/2001/XMLSchema-instance">
      <MarkdownBlockBase
        xsi:type="MarkdownParagraphBlock"
        item_id="42ce7188-c655-4c15-8f91-e38795506fa3"
        item_type="NormalParagraph"
        item_footer=""
        trans_unit_id="42ce7188-c655-4c15-8f91-e38795506fa3">
        <Lines>
          <MarkdownLine>
            <LineId>d2c276ff-5a95-42a3-9679-4224567fb6c1</LineId>
            <paragraph_segments>
              <MarkdownSegment
                trans_unit_id="101">
                <SegmentId>77470685-961a-491e-accf-1acfd9701d8e</SegmentId>
                <InternalNormalItem
                  internal_item_id="1"
                  internal_item_parent_id="101"
                  trans_unit_id="101-1"
                  internal_item_type="Normal">
                  <internal_items />
                </InternalNormalItem>
              </MarkdownSegment>
            </paragraph_segments>
            <PrefixWSLength>0</PrefixWSLength>
            <SuffixWSLength>0</SuffixWSLength>
          </MarkdownLine>
          <MarkdownLine>
            <LineId>be9844a3-1526-4de6-b648-9e80fdb99d02</LineId>
            <paragraph_segments>
              <MarkdownSegment
                trans_unit_id="102">
                <SegmentId>1676a686-944a-4089-840f-d4d1bc1be34a</SegmentId>
                <InternalNormalItem
                  internal_item_id="1"
                  internal_item_parent_id="102"
                  trans_unit_id="102-1"
                  internal_item_type="Normal">
                  <internal_items />
                </InternalNormalItem>
              </MarkdownSegment>
            </paragraph_segments>
            <PrefixWSLength>0</PrefixWSLength>
            <SuffixWSLength>0</SuffixWSLength>
          </MarkdownLine>
        </Lines>
        <paragraph_segments>
          <MarkdownSegment
            trans_unit_id="101">
            <SegmentId>77470685-961a-491e-accf-1acfd9701d8e</SegmentId>
            <InternalNormalItem
              internal_item_id="1"
              internal_item_parent_id="101"
              trans_unit_id="101-1"
              internal_item_type="Normal">
              <internal_items />
            </InternalNormalItem>
          </MarkdownSegment>
          <MarkdownSegment
            trans_unit_id="102">
            <SegmentId>1676a686-944a-4089-840f-d4d1bc1be34a</SegmentId>
            <InternalNormalItem
              internal_item_id="1"
              internal_item_parent_id="102"
              trans_unit_id="102-1"
              internal_item_type="Normal">
              <internal_items />
            </InternalNormalItem>
          </MarkdownSegment>
        </paragraph_segments>
      </MarkdownBlockBase>
      <MarkdownBlockBase
        xsi:type="MarkdownHeaderBlock"
        item_id="0552637c-838a-45ec-8f66-ec5534ef6ccf"
        item_type="Header"
        item_footer="footer_not_set"
        trans_unit_id="0552637c-838a-45ec-8f66-ec5534ef6ccf">
        <segment
          trans_unit_id="103">
          <SegmentId>b1da3728-22fc-4ace-b3da-71e1331f559c</SegmentId>
          <InternalNormalItem
            internal_item_id="1"
            internal_item_parent_id="103"
            trans_unit_id="103-1"
            internal_item_type="Normal">
            <internal_items />
          </InternalNormalItem>
        </segment>
        <header_type>Star</header_type>
        <header_level>1</header_level>
      </MarkdownBlockBase>
      <MarkdownBlockBase
        xsi:type="MarkdownParagraphBlock"
        item_id="fb047d2f-eab0-48eb-b8a4-6a36b8bbd812"
        item_type="NormalParagraph"
        item_footer=""
        trans_unit_id="fb047d2f-eab0-48eb-b8a4-6a36b8bbd812">
        <Lines>
          <MarkdownLine>
            <LineId>31818680-44bd-4124-835d-2fbf6b24e49a</LineId>
            <paragraph_segments>
              <MarkdownSegment
                trans_unit_id="104">
                <SegmentId>64671150-0fd7-4ba4-a7d3-4393a53d62dd</SegmentId>
                <InternalNormalItem
                  internal_item_id="1"
                  internal_item_parent_id="104"
                  trans_unit_id="104-1"
                  internal_item_type="Normal">
                  <internal_items />
                </InternalNormalItem>
              </MarkdownSegment>
              <MarkdownSegment
                trans_unit_id="105">
                <SegmentId>aeeb3e45-4ac3-4142-bf1d-c782c72af36b</SegmentId>
                <InternalNormalItem
                  internal_item_id="1"
                  internal_item_parent_id="105"
                  trans_unit_id="105-1"
                  internal_item_type="Normal">
                  <internal_items />
                </InternalNormalItem>
              </MarkdownSegment>
            </paragraph_segments>
            <PrefixWSLength>0</PrefixWSLength>
            <SuffixWSLength>0</SuffixWSLength>
          </MarkdownLine>
        </Lines>
        <paragraph_segments>
          <MarkdownSegment
            trans_unit_id="104">
            <SegmentId>64671150-0fd7-4ba4-a7d3-4393a53d62dd</SegmentId>
            <InternalNormalItem
              internal_item_id="1"
              internal_item_parent_id="104"
              trans_unit_id="104-1"
              internal_item_type="Normal">
              <internal_items />
            </InternalNormalItem>
          </MarkdownSegment>
          <MarkdownSegment
            trans_unit_id="105">
            <SegmentId>aeeb3e45-4ac3-4142-bf1d-c782c72af36b</SegmentId>
            <InternalNormalItem
              internal_item_id="1"
              internal_item_parent_id="105"
              trans_unit_id="105-1"
              internal_item_type="Normal">
              <internal_items />
            </InternalNormalItem>
          </MarkdownSegment>
        </paragraph_segments>
      </MarkdownBlockBase>
      <MarkdownBlockBase
        xsi:type="MarkdownParagraphBlock"
        item_id="8e115de7-4ab6-4c93-bfc1-15f708b546f3"
        item_type="NormalParagraph"
        item_footer=""
        trans_unit_id="8e115de7-4ab6-4c93-bfc1-15f708b546f3">
        <Lines>
          <MarkdownLine>
            <LineId>70607389-8fc3-43fa-bf53-764bc9419b56</LineId>
            <paragraph_segments>
              <MarkdownSegment
                trans_unit_id="106">
                <SegmentId>98a59af9-426b-487b-8ee5-769de03433c4</SegmentId>
                <InternalNormalItem
                  internal_item_id="1"
                  internal_item_parent_id="106"
                  trans_unit_id="106-1"
                  internal_item_type="Normal">
                  <internal_items />
                </InternalNormalItem>
                <LinkItem
                  internal_item_id="2"
                  internal_item_parent_id="106"
                  trans_unit_id="106-2"
                  internal_item_type="Link">
                  <internal_items />
                  <internal_link_type>Inline</internal_link_type>
                  <internal_link_text>Windows-based containers: Modern app development with enterprise-grade control</internal_link_text>
                  <internal_link_url>https://youtu.be/Ryx3o0rD5lY</internal_link_url>
                  <internal_link_title />
                </LinkItem>
                <InternalNormalItem
                  internal_item_id="3"
                  internal_item_parent_id="106"
                  trans_unit_id="106-3"
                  internal_item_type="Normal">
                  <internal_items />
                </InternalNormalItem>
              </MarkdownSegment>
            </paragraph_segments>
            <PrefixWSLength>0</PrefixWSLength>
            <SuffixWSLength>0</SuffixWSLength>
          </MarkdownLine>
        </Lines>
        <paragraph_segments>
          <MarkdownSegment
            trans_unit_id="106">
            <SegmentId>98a59af9-426b-487b-8ee5-769de03433c4</SegmentId>
            <InternalNormalItem
              internal_item_id="1"
              internal_item_parent_id="106"
              trans_unit_id="106-1"
              internal_item_type="Normal">
              <internal_items />
            </InternalNormalItem>
            <LinkItem
              internal_item_id="2"
              internal_item_parent_id="106"
              trans_unit_id="106-2"
              internal_item_type="Link">
              <internal_items />
              <internal_link_type>Inline</internal_link_type>
              <internal_link_text>Windows-based containers: Modern app development with enterprise-grade control</internal_link_text>
              <internal_link_url>https://youtu.be/Ryx3o0rD5lY</internal_link_url>
              <internal_link_title />
            </LinkItem>
            <InternalNormalItem
              internal_item_id="3"
              internal_item_parent_id="106"
              trans_unit_id="106-3"
              internal_item_type="Normal">
              <internal_items />
            </InternalNormalItem>
          </MarkdownSegment>
        </paragraph_segments>
      </MarkdownBlockBase>
      <MarkdownBlockBase
        xsi:type="MarkdownHeaderBlock"
        item_id="24dd804f-8353-4926-a463-550b09f3df53"
        item_type="Header"
        item_footer="footer_not_set"
        trans_unit_id="24dd804f-8353-4926-a463-550b09f3df53">
        <segment
          trans_unit_id="107">
          <SegmentId>2d51e733-65cd-45a1-a937-eccfdbd38f0e</SegmentId>
          <InternalNormalItem
            internal_item_id="1"
            internal_item_parent_id="107"
            trans_unit_id="107-1"
            internal_item_type="Normal">
            <internal_items />
          </InternalNormalItem>
        </segment>
        <header_type>Star</header_type>
        <header_level>2</header_level>
      </MarkdownBlockBase>
      <MarkdownBlockBase
        xsi:type="MarkdownParagraphBlock"
        item_id="55cc5b32-89ca-4aa1-8dd9-f37fa71c5217"
        item_type="NormalParagraph"
        item_footer=""
        trans_unit_id="55cc5b32-89ca-4aa1-8dd9-f37fa71c5217">
        <Lines>
          <MarkdownLine>
            <LineId>e5a5b01f-daa3-43b0-bfe9-7caebfd6f453</LineId>
            <paragraph_segments>
              <MarkdownSegment
                trans_unit_id="108">
                <SegmentId>93269760-db32-422a-8046-32c4920a632a</SegmentId>
                <InternalNormalItem
                  internal_item_id="1"
                  internal_item_parent_id="108"
                  trans_unit_id="108-1"
                  internal_item_type="Normal">
                  <internal_items />
                </InternalNormalItem>
              </MarkdownSegment>
            </paragraph_segments>
            <PrefixWSLength>0</PrefixWSLength>
            <SuffixWSLength>0</SuffixWSLength>
          </MarkdownLine>
        </Lines>
        <paragraph_segments>
          <MarkdownSegment
            trans_unit_id="108">
            <SegmentId>93269760-db32-422a-8046-32c4920a632a</SegmentId>
            <InternalNormalItem
              internal_item_id="1"
              internal_item_parent_id="108"
              trans_unit_id="108-1"
              internal_item_type="Normal">
              <internal_items />
            </InternalNormalItem>
          </MarkdownSegment>
        </paragraph_segments>
      </MarkdownBlockBase>
      <MarkdownBlockBase
        xsi:type="MarkdownParagraphBlock"
        item_id="4c489f1a-eeeb-461c-866d-ad2c194076c0"
        item_type="NormalParagraph"
        item_footer=""
        trans_unit_id="4c489f1a-eeeb-461c-866d-ad2c194076c0">
        <Lines>
          <MarkdownLine>
            <LineId>4e6ccc09-3d7b-4962-8157-adbf75e43ec8</LineId>
            <paragraph_segments>
              <MarkdownSegment
                trans_unit_id="109">
                <SegmentId>c1e0aafd-7f28-4851-ac77-296ac0cb95b0</SegmentId>
                <InternalNormalItem
                  internal_item_id="1"
                  internal_item_parent_id="109"
                  trans_unit_id="109-1"
                  internal_item_type="Normal">
                  <internal_items />
                </InternalNormalItem>
              </MarkdownSegment>
              <MarkdownSegment
                trans_unit_id="110">
                <SegmentId>ce95787f-267f-49f1-82ef-d1e6d23846a9</SegmentId>
                <InternalNormalItem
                  internal_item_id="1"
                  internal_item_parent_id="110"
                  trans_unit_id="110-1"
                  internal_item_type="Normal">
                  <internal_items />
                </InternalNormalItem>
              </MarkdownSegment>
            </paragraph_segments>
            <PrefixWSLength>0</PrefixWSLength>
            <SuffixWSLength>0</SuffixWSLength>
          </MarkdownLine>
        </Lines>
        <paragraph_segments>
          <MarkdownSegment
            trans_unit_id="109">
            <SegmentId>c1e0aafd-7f28-4851-ac77-296ac0cb95b0</SegmentId>
            <InternalNormalItem
              internal_item_id="1"
              internal_item_parent_id="109"
              trans_unit_id="109-1"
              internal_item_type="Normal">
              <internal_items />
            </InternalNormalItem>
          </MarkdownSegment>
          <MarkdownSegment
            trans_unit_id="110">
            <SegmentId>ce95787f-267f-49f1-82ef-d1e6d23846a9</SegmentId>
            <InternalNormalItem
              internal_item_id="1"
              internal_item_parent_id="110"
              trans_unit_id="110-1"
              internal_item_type="Normal">
              <internal_items />
            </InternalNormalItem>
          </MarkdownSegment>
        </paragraph_segments>
      </MarkdownBlockBase>
      <MarkdownBlockBase
        xsi:type="MarkdownParagraphBlock"
        item_id="eb5bbd70-4a7c-4002-b5d2-358333c31bcc"
        item_type="NormalParagraph"
        item_footer=""
        trans_unit_id="eb5bbd70-4a7c-4002-b5d2-358333c31bcc">
        <Lines>
          <MarkdownLine>
            <LineId>d87e1965-6faa-4890-9fbe-073ed45c05ce</LineId>
            <paragraph_segments>
              <MarkdownSegment
                trans_unit_id="111">
                <SegmentId>6c2c3101-3220-46fd-818e-45b3256de911</SegmentId>
                <InternalNormalItem
                  internal_item_id="1"
                  internal_item_parent_id="111"
                  trans_unit_id="111-1"
                  internal_item_type="Normal">
                  <internal_items />
                </InternalNormalItem>
              </MarkdownSegment>
              <MarkdownSegment
                trans_unit_id="112">
                <SegmentId>f35d53aa-fce1-4c18-a2d3-91f5a7f2808b</SegmentId>
                <InternalNormalItem
                  internal_item_id="1"
                  internal_item_parent_id="112"
                  trans_unit_id="112-1"
                  internal_item_type="Normal">
                  <internal_items />
                </InternalNormalItem>
                <LinkItem
                  internal_item_id="2"
                  internal_item_parent_id="112"
                  trans_unit_id="112-2"
                  internal_item_type="Link">
                  <internal_items />
                  <internal_link_type>Inline</internal_link_type>
                  <internal_link_text>Docker</internal_link_text>
                  <internal_link_url>https://www.docker.com/</internal_link_url>
                  <internal_link_title />
                </LinkItem>
                <InternalNormalItem
                  internal_item_id="3"
                  internal_item_parent_id="112"
                  trans_unit_id="112-3"
                  internal_item_type="Normal">
                  <internal_items />
                </InternalNormalItem>
              </MarkdownSegment>
            </paragraph_segments>
            <PrefixWSLength>0</PrefixWSLength>
            <SuffixWSLength>0</SuffixWSLength>
          </MarkdownLine>
        </Lines>
        <paragraph_segments>
          <MarkdownSegment
            trans_unit_id="111">
            <SegmentId>6c2c3101-3220-46fd-818e-45b3256de911</SegmentId>
            <InternalNormalItem
              internal_item_id="1"
              internal_item_parent_id="111"
              trans_unit_id="111-1"
              internal_item_type="Normal">
              <internal_items />
            </InternalNormalItem>
          </MarkdownSegment>
          <MarkdownSegment
            trans_unit_id="112">
            <SegmentId>f35d53aa-fce1-4c18-a2d3-91f5a7f2808b</SegmentId>
            <InternalNormalItem
              internal_item_id="1"
              internal_item_parent_id="112"
              trans_unit_id="112-1"
              internal_item_type="Normal">
              <internal_items />
            </InternalNormalItem>
            <LinkItem
              internal_item_id="2"
              internal_item_parent_id="112"
              trans_unit_id="112-2"
              internal_item_type="Link">
              <internal_items />
              <internal_link_type>Inline</internal_link_type>
              <internal_link_text>Docker</internal_link_text>
              <internal_link_url>https://www.docker.com/</internal_link_url>
              <internal_link_title />
            </LinkItem>
            <InternalNormalItem
              internal_item_id="3"
              internal_item_parent_id="112"
              trans_unit_id="112-3"
              internal_item_type="Normal">
              <internal_items />
            </InternalNormalItem>
          </MarkdownSegment>
        </paragraph_segments>
      </MarkdownBlockBase>
      <MarkdownBlockBase
        xsi:type="MarkdownHeaderBlock"
        item_id="2a8f217e-55c0-4049-b267-a8e12bac0ed1"
        item_type="Header"
        item_footer="footer_not_set"
        trans_unit_id="2a8f217e-55c0-4049-b267-a8e12bac0ed1">
        <segment
          trans_unit_id="113">
          <SegmentId>c85105df-817f-4e2d-ba96-b872b7cbc346</SegmentId>
          <InternalNormalItem
            internal_item_id="1"
            internal_item_parent_id="113"
            trans_unit_id="113-1"
            internal_item_type="Normal">
            <internal_items />
          </InternalNormalItem>
        </segment>
        <header_type>Star</header_type>
        <header_level>2</header_level>
      </MarkdownBlockBase>
      <MarkdownBlockBase
        xsi:type="MarkdownParagraphBlock"
        item_id="0a76430a-d37c-4283-8a50-2cc1b0360e03"
        item_type="NormalParagraph"
        item_footer=""
        trans_unit_id="0a76430a-d37c-4283-8a50-2cc1b0360e03">
        <Lines>
          <MarkdownLine>
            <LineId>83194ae3-34e8-4dfb-9ea7-f71d70ff9553</LineId>
            <paragraph_segments>
              <MarkdownSegment
                trans_unit_id="114">
                <SegmentId>9553b46b-41a8-4189-a593-c705f667968d</SegmentId>
                <InternalNormalItem
                  internal_item_id="1"
                  internal_item_parent_id="114"
                  trans_unit_id="114-1"
                  internal_item_type="Normal">
                  <internal_items />
                </InternalNormalItem>
              </MarkdownSegment>
              <MarkdownSegment
                trans_unit_id="115">
                <SegmentId>0b10a667-ac52-409f-946b-690fe7801395</SegmentId>
                <InternalNormalItem
                  internal_item_id="1"
                  internal_item_parent_id="115"
                  trans_unit_id="115-1"
                  internal_item_type="Normal">
                  <internal_items />
                </InternalNormalItem>
              </MarkdownSegment>
              <MarkdownSegment
                trans_unit_id="116">
                <SegmentId>a88b7eb7-298b-41dc-99a9-61a4f901db33</SegmentId>
                <InternalNormalItem
                  internal_item_id="1"
                  internal_item_parent_id="116"
                  trans_unit_id="116-1"
                  internal_item_type="Normal">
                  <internal_items />
                </InternalNormalItem>
              </MarkdownSegment>
            </paragraph_segments>
            <PrefixWSLength>0</PrefixWSLength>
            <SuffixWSLength>2</SuffixWSLength>
          </MarkdownLine>
          <MarkdownLine>
            <LineId>5df44c6f-cbe9-4243-94d2-fca714f7874a</LineId>
            <paragraph_segments>
              <MarkdownSegment
                trans_unit_id="117">
                <SegmentId>127e06f7-9340-444a-adec-0c75d246086b</SegmentId>
                <LinkItem
                  internal_item_id="1"
                  internal_item_parent_id="117"
                  trans_unit_id="117-1"
                  internal_item_type="Link">
                  <internal_items />
                  <internal_link_type>Inline</internal_link_type>
                  <internal_link_text>This blog post</internal_link_text>
                  <internal_link_url>http://azure.microsoft.com/blog/2015/08/17/containers-docker-windows-and-trends/</internal_link_url>
                  <internal_link_title />
                </LinkItem>
                <InternalNormalItem
                  internal_item_id="2"
                  internal_item_parent_id="117"
                  trans_unit_id="117-2"
                  internal_item_type="Normal">
                  <internal_items />
                </InternalNormalItem>
              </MarkdownSegment>
            </paragraph_segments>
            <PrefixWSLength>0</PrefixWSLength>
            <SuffixWSLength>0</SuffixWSLength>
          </MarkdownLine>
        </Lines>
        <paragraph_segments>
          <MarkdownSegment
            trans_unit_id="114">
            <SegmentId>9553b46b-41a8-4189-a593-c705f667968d</SegmentId>
            <InternalNormalItem
              internal_item_id="1"
              internal_item_parent_id="114"
              trans_unit_id="114-1"
              internal_item_type="Normal">
              <internal_items />
            </InternalNormalItem>
          </MarkdownSegment>
          <MarkdownSegment
            trans_unit_id="115">
            <SegmentId>0b10a667-ac52-409f-946b-690fe7801395</SegmentId>
            <InternalNormalItem
              internal_item_id="1"
              internal_item_parent_id="115"
              trans_unit_id="115-1"
              internal_item_type="Normal">
              <internal_items />
            </InternalNormalItem>
          </MarkdownSegment>
          <MarkdownSegment
            trans_unit_id="116">
            <SegmentId>a88b7eb7-298b-41dc-99a9-61a4f901db33</SegmentId>
            <InternalNormalItem
              internal_item_id="1"
              internal_item_parent_id="116"
              trans_unit_id="116-1"
              internal_item_type="Normal">
              <internal_items />
            </InternalNormalItem>
          </MarkdownSegment>
          <MarkdownSegment
            trans_unit_id="117">
            <SegmentId>127e06f7-9340-444a-adec-0c75d246086b</SegmentId>
            <LinkItem
              internal_item_id="1"
              internal_item_parent_id="117"
              trans_unit_id="117-1"
              internal_item_type="Link">
              <internal_items />
              <internal_link_type>Inline</internal_link_type>
              <internal_link_text>This blog post</internal_link_text>
              <internal_link_url>http://azure.microsoft.com/blog/2015/08/17/containers-docker-windows-and-trends/</internal_link_url>
              <internal_link_title />
            </LinkItem>
            <InternalNormalItem
              internal_item_id="2"
              internal_item_parent_id="117"
              trans_unit_id="117-2"
              internal_item_type="Normal">
              <internal_items />
            </InternalNormalItem>
          </MarkdownSegment>
        </paragraph_segments>
      </MarkdownBlockBase>
      <MarkdownBlockBase
        xsi:type="MarkdownParagraphBlock"
        item_id="3c6672b1-47fb-4751-8d7d-b22519444b39"
        item_type="NormalParagraph"
        item_footer=""
        trans_unit_id="3c6672b1-47fb-4751-8d7d-b22519444b39">
        <Lines>
          <MarkdownLine>
            <LineId>da302a94-e586-4331-9d28-065942798c56</LineId>
            <paragraph_segments>
              <MarkdownSegment
                trans_unit_id="118">
                <SegmentId>792b11dc-3b27-408a-ba4c-6bc6426b2179</SegmentId>
                <InternalNormalItem
                  internal_item_id="1"
                  internal_item_parent_id="118"
                  trans_unit_id="118-1"
                  internal_item_type="Normal">
                  <internal_items />
                </InternalNormalItem>
              </MarkdownSegment>
            </paragraph_segments>
            <PrefixWSLength>0</PrefixWSLength>
            <SuffixWSLength>0</SuffixWSLength>
          </MarkdownLine>
        </Lines>
        <paragraph_segments>
          <MarkdownSegment
            trans_unit_id="118">
            <SegmentId>792b11dc-3b27-408a-ba4c-6bc6426b2179</SegmentId>
            <InternalNormalItem
              internal_item_id="1"
              internal_item_parent_id="118"
              trans_unit_id="118-1"
              internal_item_type="Normal">
              <internal_items />
            </InternalNormalItem>
          </MarkdownSegment>
        </paragraph_segments>
      </MarkdownBlockBase>
      <MarkdownBlockBase
        xsi:type="MarkdownParagraphBlock"
        item_id="fde7d3b1-d83a-4a77-855c-ac08da56ed3d"
        item_type="NormalParagraph"
        item_footer=""
        trans_unit_id="fde7d3b1-d83a-4a77-855c-ac08da56ed3d">
        <Lines>
          <MarkdownLine>
            <LineId>7ba5b35a-caa8-4fc9-bef7-39094483fdf0</LineId>
            <paragraph_segments>
              <MarkdownSegment
                trans_unit_id="119">
                <SegmentId>319335be-d7ca-4d81-a930-c2431b3f4ce0</SegmentId>
                <MarkdownInternalBoldItem
                  internal_item_id="1"
                  internal_item_parent_id="119"
                  trans_unit_id="119-1"
                  internal_item_type="Bold">
                  <internal_items />
                  <internal_itatic_bold_item_type>Star</internal_itatic_bold_item_type>
                </MarkdownInternalBoldItem>
                <InternalNormalItem
                  internal_item_id="2"
                  internal_item_parent_id="119"
                  trans_unit_id="119-2"
                  internal_item_type="Normal">
                  <internal_items />
                </InternalNormalItem>
              </MarkdownSegment>
              <MarkdownSegment
                trans_unit_id="120">
                <SegmentId>e5ae7d4e-a095-4ae2-960a-1a210ebfad62</SegmentId>
                <InternalNormalItem
                  internal_item_id="1"
                  internal_item_parent_id="120"
                  trans_unit_id="120-1"
                  internal_item_type="Normal">
                  <internal_items />
                </InternalNormalItem>
              </MarkdownSegment>
            </paragraph_segments>
            <PrefixWSLength>0</PrefixWSLength>
            <SuffixWSLength>0</SuffixWSLength>
          </MarkdownLine>
        </Lines>
        <paragraph_segments>
          <MarkdownSegment
            trans_unit_id="119">
            <SegmentId>319335be-d7ca-4d81-a930-c2431b3f4ce0</SegmentId>
            <MarkdownInternalBoldItem
              internal_item_id="1"
              internal_item_parent_id="119"
              trans_unit_id="119-1"
              internal_item_type="Bold">
              <internal_items />
              <internal_itatic_bold_item_type>Star</internal_itatic_bold_item_type>
            </MarkdownInternalBoldItem>
            <InternalNormalItem
              internal_item_id="2"
              internal_item_parent_id="119"
              trans_unit_id="119-2"
              internal_item_type="Normal">
              <internal_items />
            </InternalNormalItem>
          </MarkdownSegment>
          <MarkdownSegment
            trans_unit_id="120">
            <SegmentId>e5ae7d4e-a095-4ae2-960a-1a210ebfad62</SegmentId>
            <InternalNormalItem
              internal_item_id="1"
              internal_item_parent_id="120"
              trans_unit_id="120-1"
              internal_item_type="Normal">
              <internal_items />
            </InternalNormalItem>
          </MarkdownSegment>
        </paragraph_segments>
      </MarkdownBlockBase>
      <MarkdownBlockBase
        xsi:type="MarkdownParagraphBlock"
        item_id="ff1b4566-7f9a-459c-99da-2cf14a66b0d4"
        item_type="NormalParagraph"
        item_footer=""
        trans_unit_id="ff1b4566-7f9a-459c-99da-2cf14a66b0d4">
        <Lines>
          <MarkdownLine>
            <LineId>611b0bd1-182d-4131-b8b5-6cf9f1f023c0</LineId>
            <paragraph_segments>
              <MarkdownSegment
                trans_unit_id="121">
                <SegmentId>56247596-66f9-410c-ab8e-2a86f71120c1</SegmentId>
                <MarkdownInternalBoldItem
                  internal_item_id="1"
                  internal_item_parent_id="121"
                  trans_unit_id="121-1"
                  internal_item_type="Bold">
                  <internal_items />
                  <internal_itatic_bold_item_type>Star</internal_itatic_bold_item_type>
                </MarkdownInternalBoldItem>
                <InternalNormalItem
                  internal_item_id="2"
                  internal_item_parent_id="121"
                  trans_unit_id="121-2"
                  internal_item_type="Normal">
                  <internal_items />
                </InternalNormalItem>
              </MarkdownSegment>
              <MarkdownSegment
                trans_unit_id="122">
                <SegmentId>9a2f9808-f7a6-4abe-9d85-4cc8f8ed0ce0</SegmentId>
                <InternalNormalItem
                  internal_item_id="1"
                  internal_item_parent_id="122"
                  trans_unit_id="122-1"
                  internal_item_type="Normal">
                  <internal_items />
                </InternalNormalItem>
              </MarkdownSegment>
              <MarkdownSegment
                trans_unit_id="123">
                <SegmentId>15fec0bd-5774-4442-87a1-1d2c6b3b617e</SegmentId>
                <InternalNormalItem
                  internal_item_id="1"
                  internal_item_parent_id="123"
                  trans_unit_id="123-1"
                  internal_item_type="Normal">
                  <internal_items />
                </InternalNormalItem>
              </MarkdownSegment>
              <MarkdownSegment
                trans_unit_id="124">
                <SegmentId>b260b313-4d5f-43e2-856a-db882f529c9d</SegmentId>
                <InternalNormalItem
                  internal_item_id="1"
                  internal_item_parent_id="124"
                  trans_unit_id="124-1"
                  internal_item_type="Normal">
                  <internal_items />
                </InternalNormalItem>
              </MarkdownSegment>
              <MarkdownSegment
                trans_unit_id="125">
                <SegmentId>62076ea3-9fb1-4345-9356-a3fd964e765f</SegmentId>
                <InternalNormalItem
                  internal_item_id="1"
                  internal_item_parent_id="125"
                  trans_unit_id="125-1"
                  internal_item_type="Normal">
                  <internal_items />
                </InternalNormalItem>
              </MarkdownSegment>
              <MarkdownSegment
                trans_unit_id="126">
                <SegmentId>f44e3a66-1355-40cb-ac7f-cea69db777e2</SegmentId>
                <InternalNormalItem
                  internal_item_id="1"
                  internal_item_parent_id="126"
                  trans_unit_id="126-1"
                  internal_item_type="Normal">
                  <internal_items />
                </InternalNormalItem>
              </MarkdownSegment>
              <MarkdownSegment
                trans_unit_id="127">
                <SegmentId>cc9bfd92-31a4-4768-acff-7bcabeb9350d</SegmentId>
                <InternalNormalItem
                  internal_item_id="1"
                  internal_item_parent_id="127"
                  trans_unit_id="127-1"
                  internal_item_type="Normal">
                  <internal_items />
                </InternalNormalItem>
              </MarkdownSegment>
            </paragraph_segments>
            <PrefixWSLength>0</PrefixWSLength>
            <SuffixWSLength>0</SuffixWSLength>
          </MarkdownLine>
        </Lines>
        <paragraph_segments>
          <MarkdownSegment
            trans_unit_id="121">
            <SegmentId>56247596-66f9-410c-ab8e-2a86f71120c1</SegmentId>
            <MarkdownInternalBoldItem
              internal_item_id="1"
              internal_item_parent_id="121"
              trans_unit_id="121-1"
              internal_item_type="Bold">
              <internal_items />
              <internal_itatic_bold_item_type>Star</internal_itatic_bold_item_type>
            </MarkdownInternalBoldItem>
            <InternalNormalItem
              internal_item_id="2"
              internal_item_parent_id="121"
              trans_unit_id="121-2"
              internal_item_type="Normal">
              <internal_items />
            </InternalNormalItem>
          </MarkdownSegment>
          <MarkdownSegment
            trans_unit_id="122">
            <SegmentId>9a2f9808-f7a6-4abe-9d85-4cc8f8ed0ce0</SegmentId>
            <InternalNormalItem
              internal_item_id="1"
              internal_item_parent_id="122"
              trans_unit_id="122-1"
              internal_item_type="Normal">
              <internal_items />
            </InternalNormalItem>
          </MarkdownSegment>
          <MarkdownSegment
            trans_unit_id="123">
            <SegmentId>15fec0bd-5774-4442-87a1-1d2c6b3b617e</SegmentId>
            <InternalNormalItem
              internal_item_id="1"
              internal_item_parent_id="123"
              trans_unit_id="123-1"
              internal_item_type="Normal">
              <internal_items />
            </InternalNormalItem>
          </MarkdownSegment>
          <MarkdownSegment
            trans_unit_id="124">
            <SegmentId>b260b313-4d5f-43e2-856a-db882f529c9d</SegmentId>
            <InternalNormalItem
              internal_item_id="1"
              internal_item_parent_id="124"
              trans_unit_id="124-1"
              internal_item_type="Normal">
              <internal_items />
            </InternalNormalItem>
          </MarkdownSegment>
          <MarkdownSegment
            trans_unit_id="125">
            <SegmentId>62076ea3-9fb1-4345-9356-a3fd964e765f</SegmentId>
            <InternalNormalItem
              internal_item_id="1"
              internal_item_parent_id="125"
              trans_unit_id="125-1"
              internal_item_type="Normal">
              <internal_items />
            </InternalNormalItem>
          </MarkdownSegment>
          <MarkdownSegment
            trans_unit_id="126">
            <SegmentId>f44e3a66-1355-40cb-ac7f-cea69db777e2</SegmentId>
            <InternalNormalItem
              internal_item_id="1"
              internal_item_parent_id="126"
              trans_unit_id="126-1"
              internal_item_type="Normal">
              <internal_items />
            </InternalNormalItem>
          </MarkdownSegment>
          <MarkdownSegment
            trans_unit_id="127">
            <SegmentId>cc9bfd92-31a4-4768-acff-7bcabeb9350d</SegmentId>
            <InternalNormalItem
              internal_item_id="1"
              internal_item_parent_id="127"
              trans_unit_id="127-1"
              internal_item_type="Normal">
              <internal_items />
            </InternalNormalItem>
          </MarkdownSegment>
        </paragraph_segments>
      </MarkdownBlockBase>
      <MarkdownBlockBase
        xsi:type="MarkdownParagraphBlock"
        item_id="559c1d28-f665-4108-8423-ca47715b5ec9"
        item_type="NormalParagraph"
        item_footer=""
        trans_unit_id="559c1d28-f665-4108-8423-ca47715b5ec9">
        <Lines>
          <MarkdownLine>
            <LineId>89b1ea8c-e5b4-4a44-a4da-70a64af35726</LineId>
            <paragraph_segments>
              <MarkdownSegment
                trans_unit_id="128">
                <SegmentId>da55e76f-22f4-4ed0-adde-fcf72aa7ee7f</SegmentId>
                <MarkdownInternalBoldItem
                  internal_item_id="1"
                  internal_item_parent_id="128"
                  trans_unit_id="128-1"
                  internal_item_type="Bold">
                  <internal_items />
                  <internal_itatic_bold_item_type>Star</internal_itatic_bold_item_type>
                </MarkdownInternalBoldItem>
                <InternalNormalItem
                  internal_item_id="2"
                  internal_item_parent_id="128"
                  trans_unit_id="128-2"
                  internal_item_type="Normal">
                  <internal_items />
                </InternalNormalItem>
              </MarkdownSegment>
            </paragraph_segments>
            <PrefixWSLength>0</PrefixWSLength>
            <SuffixWSLength>0</SuffixWSLength>
          </MarkdownLine>
        </Lines>
        <paragraph_segments>
          <MarkdownSegment
            trans_unit_id="128">
            <SegmentId>da55e76f-22f4-4ed0-adde-fcf72aa7ee7f</SegmentId>
            <MarkdownInternalBoldItem
              internal_item_id="1"
              internal_item_parent_id="128"
              trans_unit_id="128-1"
              internal_item_type="Bold">
              <internal_items />
              <internal_itatic_bold_item_type>Star</internal_itatic_bold_item_type>
            </MarkdownInternalBoldItem>
            <InternalNormalItem
              internal_item_id="2"
              internal_item_parent_id="128"
              trans_unit_id="128-2"
              internal_item_type="Normal">
              <internal_items />
            </InternalNormalItem>
          </MarkdownSegment>
        </paragraph_segments>
      </MarkdownBlockBase>
      <MarkdownBlockBase
        xsi:type="MarkdownParagraphBlock"
        item_id="82e7d9ed-e623-4fc7-bc69-3d6eef9ef449"
        item_type="NormalParagraph"
        item_footer=""
        trans_unit_id="82e7d9ed-e623-4fc7-bc69-3d6eef9ef449">
        <Lines>
          <MarkdownLine>
            <LineId>09867444-1e5d-4b22-8191-74f02ac130ba</LineId>
            <paragraph_segments>
              <MarkdownSegment
                trans_unit_id="129">
                <SegmentId>5f670418-eaa2-485c-80c8-d75609b1c637</SegmentId>
                <MarkdownInternalBoldItem
                  internal_item_id="1"
                  internal_item_parent_id="129"
                  trans_unit_id="129-1"
                  internal_item_type="Bold">
                  <internal_items />
                  <internal_itatic_bold_item_type>Star</internal_itatic_bold_item_type>
                </MarkdownInternalBoldItem>
                <InternalNormalItem
                  internal_item_id="2"
                  internal_item_parent_id="129"
                  trans_unit_id="129-2"
                  internal_item_type="Normal">
                  <internal_items />
                </InternalNormalItem>
              </MarkdownSegment>
              <MarkdownSegment
                trans_unit_id="130">
                <SegmentId>0abec4bc-bfc3-40ce-b55e-73bc07019e8a</SegmentId>
                <InternalNormalItem
                  internal_item_id="1"
                  internal_item_parent_id="130"
                  trans_unit_id="130-1"
                  internal_item_type="Normal">
                  <internal_items />
                </InternalNormalItem>
              </MarkdownSegment>
              <MarkdownSegment
                trans_unit_id="131">
                <SegmentId>bc21f9d5-4556-4c25-9d7b-a06f69e441d9</SegmentId>
                <InternalNormalItem
                  internal_item_id="1"
                  internal_item_parent_id="131"
                  trans_unit_id="131-1"
                  internal_item_type="Normal">
                  <internal_items />
                </InternalNormalItem>
              </MarkdownSegment>
              <MarkdownSegment
                trans_unit_id="132">
                <SegmentId>1b21c50e-ffa4-436f-94a3-5fae73730a18</SegmentId>
                <InternalNormalItem
                  internal_item_id="1"
                  internal_item_parent_id="132"
                  trans_unit_id="132-1"
                  internal_item_type="Normal">
                  <internal_items />
                </InternalNormalItem>
              </MarkdownSegment>
            </paragraph_segments>
            <PrefixWSLength>0</PrefixWSLength>
            <SuffixWSLength>0</SuffixWSLength>
          </MarkdownLine>
        </Lines>
        <paragraph_segments>
          <MarkdownSegment
            trans_unit_id="129">
            <SegmentId>5f670418-eaa2-485c-80c8-d75609b1c637</SegmentId>
            <MarkdownInternalBoldItem
              internal_item_id="1"
              internal_item_parent_id="129"
              trans_unit_id="129-1"
              internal_item_type="Bold">
              <internal_items />
              <internal_itatic_bold_item_type>Star</internal_itatic_bold_item_type>
            </MarkdownInternalBoldItem>
            <InternalNormalItem
              internal_item_id="2"
              internal_item_parent_id="129"
              trans_unit_id="129-2"
              internal_item_type="Normal">
              <internal_items />
            </InternalNormalItem>
          </MarkdownSegment>
          <MarkdownSegment
            trans_unit_id="130">
            <SegmentId>0abec4bc-bfc3-40ce-b55e-73bc07019e8a</SegmentId>
            <InternalNormalItem
              internal_item_id="1"
              internal_item_parent_id="130"
              trans_unit_id="130-1"
              internal_item_type="Normal">
              <internal_items />
            </InternalNormalItem>
          </MarkdownSegment>
          <MarkdownSegment
            trans_unit_id="131">
            <SegmentId>bc21f9d5-4556-4c25-9d7b-a06f69e441d9</SegmentId>
            <InternalNormalItem
              internal_item_id="1"
              internal_item_parent_id="131"
              trans_unit_id="131-1"
              internal_item_type="Normal">
              <internal_items />
            </InternalNormalItem>
          </MarkdownSegment>
          <MarkdownSegment
            trans_unit_id="132">
            <SegmentId>1b21c50e-ffa4-436f-94a3-5fae73730a18</SegmentId>
            <InternalNormalItem
              internal_item_id="1"
              internal_item_parent_id="132"
              trans_unit_id="132-1"
              internal_item_type="Normal">
              <internal_items />
            </InternalNormalItem>
          </MarkdownSegment>
        </paragraph_segments>
      </MarkdownBlockBase>
      <MarkdownBlockBase
        xsi:type="MarkdownParagraphBlock"
        item_id="6b748dc5-433f-4f1f-971c-99d5a222704f"
        item_type="NormalParagraph"
        item_footer=""
        trans_unit_id="6b748dc5-433f-4f1f-971c-99d5a222704f">
        <Lines>
          <MarkdownLine>
            <LineId>5ba5412b-f5ea-4c3f-9464-5a3af121dbb6</LineId>
            <paragraph_segments>
              <MarkdownSegment
                trans_unit_id="133">
                <SegmentId>d3b4af80-03cb-4e2e-b242-5f4ba387def7</SegmentId>
                <MarkdownInternalBoldItem
                  internal_item_id="1"
                  internal_item_parent_id="133"
                  trans_unit_id="133-1"
                  internal_item_type="Bold">
                  <internal_items />
                  <internal_itatic_bold_item_type>Star</internal_itatic_bold_item_type>
                </MarkdownInternalBoldItem>
                <InternalNormalItem
                  internal_item_id="2"
                  internal_item_parent_id="133"
                  trans_unit_id="133-2"
                  internal_item_type="Normal">
                  <internal_items />
                </InternalNormalItem>
              </MarkdownSegment>
              <MarkdownSegment
                trans_unit_id="134">
                <SegmentId>b6f9e07b-90ef-48b2-b8a4-a2ad076f7d3c</SegmentId>
                <InternalNormalItem
                  internal_item_id="1"
                  internal_item_parent_id="134"
                  trans_unit_id="134-1"
                  internal_item_type="Normal">
                  <internal_items />
                </InternalNormalItem>
              </MarkdownSegment>
              <MarkdownSegment
                trans_unit_id="135">
                <SegmentId>f58473d6-eba8-403c-b312-3ed5d39de842</SegmentId>
                <InternalNormalItem
                  internal_item_id="1"
                  internal_item_parent_id="135"
                  trans_unit_id="135-1"
                  internal_item_type="Normal">
                  <internal_items />
                </InternalNormalItem>
              </MarkdownSegment>
            </paragraph_segments>
            <PrefixWSLength>0</PrefixWSLength>
            <SuffixWSLength>0</SuffixWSLength>
          </MarkdownLine>
        </Lines>
        <paragraph_segments>
          <MarkdownSegment
            trans_unit_id="133">
            <SegmentId>d3b4af80-03cb-4e2e-b242-5f4ba387def7</SegmentId>
            <MarkdownInternalBoldItem
              internal_item_id="1"
              internal_item_parent_id="133"
              trans_unit_id="133-1"
              internal_item_type="Bold">
              <internal_items />
              <internal_itatic_bold_item_type>Star</internal_itatic_bold_item_type>
            </MarkdownInternalBoldItem>
            <InternalNormalItem
              internal_item_id="2"
              internal_item_parent_id="133"
              trans_unit_id="133-2"
              internal_item_type="Normal">
              <internal_items />
            </InternalNormalItem>
          </MarkdownSegment>
          <MarkdownSegment
            trans_unit_id="134">
            <SegmentId>b6f9e07b-90ef-48b2-b8a4-a2ad076f7d3c</SegmentId>
            <InternalNormalItem
              internal_item_id="1"
              internal_item_parent_id="134"
              trans_unit_id="134-1"
              internal_item_type="Normal">
              <internal_items />
            </InternalNormalItem>
          </MarkdownSegment>
          <MarkdownSegment
            trans_unit_id="135">
            <SegmentId>f58473d6-eba8-403c-b312-3ed5d39de842</SegmentId>
            <InternalNormalItem
              internal_item_id="1"
              internal_item_parent_id="135"
              trans_unit_id="135-1"
              internal_item_type="Normal">
              <internal_items />
            </InternalNormalItem>
          </MarkdownSegment>
        </paragraph_segments>
      </MarkdownBlockBase>
      <MarkdownBlockBase
        xsi:type="MarkdownParagraphBlock"
        item_id="aca91521-1416-4cf7-a347-f2287fbf41ac"
        item_type="NormalParagraph"
        item_footer=""
        trans_unit_id="aca91521-1416-4cf7-a347-f2287fbf41ac">
        <Lines>
          <MarkdownLine>
            <LineId>c1568f22-a2c8-4ce9-bfc7-d9059f61e66a</LineId>
            <paragraph_segments>
              <MarkdownSegment
                trans_unit_id="136">
                <SegmentId>dd900b85-ae13-4850-8c7e-de2785ca28d7</SegmentId>
                <MarkdownInternalBoldItem
                  internal_item_id="1"
                  internal_item_parent_id="136"
                  trans_unit_id="136-1"
                  internal_item_type="Bold">
                  <internal_items />
                  <internal_itatic_bold_item_type>Star</internal_itatic_bold_item_type>
                </MarkdownInternalBoldItem>
                <InternalNormalItem
                  internal_item_id="2"
                  internal_item_parent_id="136"
                  trans_unit_id="136-2"
                  internal_item_type="Normal">
                  <internal_items />
                </InternalNormalItem>
              </MarkdownSegment>
              <MarkdownSegment
                trans_unit_id="137">
                <SegmentId>5054f493-ce11-493b-bea5-a2b13ae7eca9</SegmentId>
                <InternalNormalItem
                  internal_item_id="1"
                  internal_item_parent_id="137"
                  trans_unit_id="137-1"
                  internal_item_type="Normal">
                  <internal_items />
                </InternalNormalItem>
              </MarkdownSegment>
            </paragraph_segments>
            <PrefixWSLength>0</PrefixWSLength>
            <SuffixWSLength>0</SuffixWSLength>
          </MarkdownLine>
        </Lines>
        <paragraph_segments>
          <MarkdownSegment
            trans_unit_id="136">
            <SegmentId>dd900b85-ae13-4850-8c7e-de2785ca28d7</SegmentId>
            <MarkdownInternalBoldItem
              internal_item_id="1"
              internal_item_parent_id="136"
              trans_unit_id="136-1"
              internal_item_type="Bold">
              <internal_items />
              <internal_itatic_bold_item_type>Star</internal_itatic_bold_item_type>
            </MarkdownInternalBoldItem>
            <InternalNormalItem
              internal_item_id="2"
              internal_item_parent_id="136"
              trans_unit_id="136-2"
              internal_item_type="Normal">
              <internal_items />
            </InternalNormalItem>
          </MarkdownSegment>
          <MarkdownSegment
            trans_unit_id="137">
            <SegmentId>5054f493-ce11-493b-bea5-a2b13ae7eca9</SegmentId>
            <InternalNormalItem
              internal_item_id="1"
              internal_item_parent_id="137"
              trans_unit_id="137-1"
              internal_item_type="Normal">
              <internal_items />
            </InternalNormalItem>
          </MarkdownSegment>
        </paragraph_segments>
      </MarkdownBlockBase>
      <MarkdownBlockBase
        xsi:type="MarkdownParagraphBlock"
        item_id="606581d6-221d-4aa8-bbd0-6b7234f01421"
        item_type="NormalParagraph"
        item_footer=""
        trans_unit_id="606581d6-221d-4aa8-bbd0-6b7234f01421">
        <Lines>
          <MarkdownLine>
            <LineId>97908742-4d00-4ed2-a61f-ecff3a1b992f</LineId>
            <paragraph_segments>
              <MarkdownSegment
                trans_unit_id="138">
                <SegmentId>45637f19-0966-4e86-a6bb-6300df5a2b90</SegmentId>
                <MarkdownInternalHtmlTag
                  internal_item_id="1"
                  internal_item_parent_id="138"
                  trans_unit_id="138-1"
                  internal_item_type="HtmlTag">
                  <internal_items />
                  <itemValue>&lt;center&gt;</itemValue>
                </MarkdownInternalHtmlTag>
                <ImageItem
                  internal_item_id="2"
                  internal_item_parent_id="138"
                  trans_unit_id="138-2"
                  internal_item_type="Image">
                  <internal_items />
                  <internal_Image_type>Inline</internal_Image_type>
                  <internal_link_text />
                  <internal_link_url>media/containerfund.png</internal_link_url>
                  <internal_link_title />
                </ImageItem>
                <MarkdownInternalHtmlTag
                  internal_item_id="3"
                  internal_item_parent_id="138"
                  trans_unit_id="138-3"
                  internal_item_type="HtmlTag">
                  <internal_items />
                  <itemValue>&lt;/center&gt;</itemValue>
                </MarkdownInternalHtmlTag>
              </MarkdownSegment>
            </paragraph_segments>
            <PrefixWSLength>0</PrefixWSLength>
            <SuffixWSLength>0</SuffixWSLength>
          </MarkdownLine>
        </Lines>
        <paragraph_segments>
          <MarkdownSegment
            trans_unit_id="138">
            <SegmentId>45637f19-0966-4e86-a6bb-6300df5a2b90</SegmentId>
            <MarkdownInternalHtmlTag
              internal_item_id="1"
              internal_item_parent_id="138"
              trans_unit_id="138-1"
              internal_item_type="HtmlTag">
              <internal_items />
              <itemValue>&lt;center&gt;</itemValue>
            </MarkdownInternalHtmlTag>
            <ImageItem
              internal_item_id="2"
              internal_item_parent_id="138"
              trans_unit_id="138-2"
              internal_item_type="Image">
              <internal_items />
              <internal_Image_type>Inline</internal_Image_type>
              <internal_link_text />
              <internal_link_url>media/containerfund.png</internal_link_url>
              <internal_link_title />
            </ImageItem>
            <MarkdownInternalHtmlTag
              internal_item_id="3"
              internal_item_parent_id="138"
              trans_unit_id="138-3"
              internal_item_type="HtmlTag">
              <internal_items />
              <itemValue>&lt;/center&gt;</itemValue>
            </MarkdownInternalHtmlTag>
          </MarkdownSegment>
        </paragraph_segments>
      </MarkdownBlockBase>
      <MarkdownBlockBase
        xsi:type="MarkdownHeaderBlock"
        item_id="ba212603-0306-47d3-a4cb-50897b5dc93f"
        item_type="Header"
        item_footer="footer_not_set"
        trans_unit_id="ba212603-0306-47d3-a4cb-50897b5dc93f">
        <segment
          trans_unit_id="139">
          <SegmentId>40cf3b36-054a-4735-b4af-692925d406e4</SegmentId>
          <InternalNormalItem
            internal_item_id="1"
            internal_item_parent_id="139"
            trans_unit_id="139-1"
            internal_item_type="Normal">
            <internal_items />
          </InternalNormalItem>
        </segment>
        <header_type>Star</header_type>
        <header_level>2</header_level>
      </MarkdownBlockBase>
      <MarkdownBlockBase
        xsi:type="MarkdownParagraphBlock"
        item_id="b87aa15d-0499-4754-8126-d81ca3267848"
        item_type="NormalParagraph"
        item_footer=""
        trans_unit_id="b87aa15d-0499-4754-8126-d81ca3267848">
        <Lines>
          <MarkdownLine>
            <LineId>26143424-af0e-4aed-b462-7a511a63a95f</LineId>
            <paragraph_segments>
              <MarkdownSegment
                trans_unit_id="140">
                <SegmentId>f2703374-8d3c-4bbb-b5d3-9b8cda8117e4</SegmentId>
                <InternalNormalItem
                  internal_item_id="1"
                  internal_item_parent_id="140"
                  trans_unit_id="140-1"
                  internal_item_type="Normal">
                  <internal_items />
                </InternalNormalItem>
              </MarkdownSegment>
              <MarkdownSegment
                trans_unit_id="141">
                <SegmentId>93331cee-96ca-4055-bf0e-33e432047e87</SegmentId>
                <InternalNormalItem
                  internal_item_id="1"
                  internal_item_parent_id="141"
                  trans_unit_id="141-1"
                  internal_item_type="Normal">
                  <internal_items />
                </InternalNormalItem>
              </MarkdownSegment>
            </paragraph_segments>
            <PrefixWSLength>0</PrefixWSLength>
            <SuffixWSLength>0</SuffixWSLength>
          </MarkdownLine>
        </Lines>
        <paragraph_segments>
          <MarkdownSegment
            trans_unit_id="140">
            <SegmentId>f2703374-8d3c-4bbb-b5d3-9b8cda8117e4</SegmentId>
            <InternalNormalItem
              internal_item_id="1"
              internal_item_parent_id="140"
              trans_unit_id="140-1"
              internal_item_type="Normal">
              <internal_items />
            </InternalNormalItem>
          </MarkdownSegment>
          <MarkdownSegment
            trans_unit_id="141">
            <SegmentId>93331cee-96ca-4055-bf0e-33e432047e87</SegmentId>
            <InternalNormalItem
              internal_item_id="1"
              internal_item_parent_id="141"
              trans_unit_id="141-1"
              internal_item_type="Normal">
              <internal_items />
            </InternalNormalItem>
          </MarkdownSegment>
        </paragraph_segments>
      </MarkdownBlockBase>
      <MarkdownBlockBase
        xsi:type="MarkdownParagraphBlock"
        item_id="40a80501-301b-4cd2-88ff-15231cacee9b"
        item_type="NormalParagraph"
        item_footer=""
        trans_unit_id="40a80501-301b-4cd2-88ff-15231cacee9b">
        <Lines>
          <MarkdownLine>
            <LineId>52d0cc60-95fb-43ed-9ddf-7e80c9096906</LineId>
            <paragraph_segments>
              <MarkdownSegment
                trans_unit_id="142">
                <SegmentId>766d7143-ef3a-42c8-ac64-f126a79f0bc5</SegmentId>
                <InternalNormalItem
                  internal_item_id="1"
                  internal_item_parent_id="142"
                  trans_unit_id="142-1"
                  internal_item_type="Normal">
                  <internal_items />
                </InternalNormalItem>
              </MarkdownSegment>
              <MarkdownSegment
                trans_unit_id="143">
                <SegmentId>25b7be71-70a8-4978-8de7-7a294485d51e</SegmentId>
                <InternalNormalItem
                  internal_item_id="1"
                  internal_item_parent_id="143"
                  trans_unit_id="143-1"
                  internal_item_type="Normal">
                  <internal_items />
                </InternalNormalItem>
              </MarkdownSegment>
              <MarkdownSegment
                trans_unit_id="144">
                <SegmentId>5d9326c1-f38f-47c6-9def-da19bd41d1a5</SegmentId>
                <InternalNormalItem
                  internal_item_id="1"
                  internal_item_parent_id="144"
                  trans_unit_id="144-1"
                  internal_item_type="Normal">
                  <internal_items />
                </InternalNormalItem>
              </MarkdownSegment>
              <MarkdownSegment
                trans_unit_id="145">
                <SegmentId>47574b69-157e-42cb-8050-e6c5abf2d01a</SegmentId>
                <InternalNormalItem
                  internal_item_id="1"
                  internal_item_parent_id="145"
                  trans_unit_id="145-1"
                  internal_item_type="Normal">
                  <internal_items />
                </InternalNormalItem>
              </MarkdownSegment>
              <MarkdownSegment
                trans_unit_id="146">
                <SegmentId>92f60420-ab4e-49b0-9794-6dd8084a477f</SegmentId>
                <InternalNormalItem
                  internal_item_id="1"
                  internal_item_parent_id="146"
                  trans_unit_id="146-1"
                  internal_item_type="Normal">
                  <internal_items />
                </InternalNormalItem>
              </MarkdownSegment>
            </paragraph_segments>
            <PrefixWSLength>0</PrefixWSLength>
            <SuffixWSLength>0</SuffixWSLength>
          </MarkdownLine>
        </Lines>
        <paragraph_segments>
          <MarkdownSegment
            trans_unit_id="142">
            <SegmentId>766d7143-ef3a-42c8-ac64-f126a79f0bc5</SegmentId>
            <InternalNormalItem
              internal_item_id="1"
              internal_item_parent_id="142"
              trans_unit_id="142-1"
              internal_item_type="Normal">
              <internal_items />
            </InternalNormalItem>
          </MarkdownSegment>
          <MarkdownSegment
            trans_unit_id="143">
            <SegmentId>25b7be71-70a8-4978-8de7-7a294485d51e</SegmentId>
            <InternalNormalItem
              internal_item_id="1"
              internal_item_parent_id="143"
              trans_unit_id="143-1"
              internal_item_type="Normal">
              <internal_items />
            </InternalNormalItem>
          </MarkdownSegment>
          <MarkdownSegment
            trans_unit_id="144">
            <SegmentId>5d9326c1-f38f-47c6-9def-da19bd41d1a5</SegmentId>
            <InternalNormalItem
              internal_item_id="1"
              internal_item_parent_id="144"
              trans_unit_id="144-1"
              internal_item_type="Normal">
              <internal_items />
            </InternalNormalItem>
          </MarkdownSegment>
          <MarkdownSegment
            trans_unit_id="145">
            <SegmentId>47574b69-157e-42cb-8050-e6c5abf2d01a</SegmentId>
            <InternalNormalItem
              internal_item_id="1"
              internal_item_parent_id="145"
              trans_unit_id="145-1"
              internal_item_type="Normal">
              <internal_items />
            </InternalNormalItem>
          </MarkdownSegment>
          <MarkdownSegment
            trans_unit_id="146">
            <SegmentId>92f60420-ab4e-49b0-9794-6dd8084a477f</SegmentId>
            <InternalNormalItem
              internal_item_id="1"
              internal_item_parent_id="146"
              trans_unit_id="146-1"
              internal_item_type="Normal">
              <internal_items />
            </InternalNormalItem>
          </MarkdownSegment>
        </paragraph_segments>
      </MarkdownBlockBase>
      <MarkdownBlockBase
        xsi:type="MarkdownParagraphBlock"
        item_id="fff8aded-e6ad-4368-85cb-8bf1a4f1e161"
        item_type="NormalParagraph"
        item_footer=""
        trans_unit_id="fff8aded-e6ad-4368-85cb-8bf1a4f1e161">
        <Lines>
          <MarkdownLine>
            <LineId>15b7e41d-fa00-42fa-9949-30249eb01e29</LineId>
            <paragraph_segments>
              <MarkdownSegment
                trans_unit_id="147">
                <SegmentId>77c95b2f-6c1f-47b6-a9fa-df7bc9fd800d</SegmentId>
                <InternalNormalItem
                  internal_item_id="1"
                  internal_item_parent_id="147"
                  trans_unit_id="147-1"
                  internal_item_type="Normal">
                  <internal_items />
                </InternalNormalItem>
              </MarkdownSegment>
              <MarkdownSegment
                trans_unit_id="148">
                <SegmentId>92a09384-dd9e-47c2-b98a-c9d44f7dce84</SegmentId>
                <InternalNormalItem
                  internal_item_id="1"
                  internal_item_parent_id="148"
                  trans_unit_id="148-1"
                  internal_item_type="Normal">
                  <internal_items />
                </InternalNormalItem>
              </MarkdownSegment>
              <MarkdownSegment
                trans_unit_id="149">
                <SegmentId>e2e256d6-e8ce-4784-9a0e-70acad341335</SegmentId>
                <InternalNormalItem
                  internal_item_id="1"
                  internal_item_parent_id="149"
                  trans_unit_id="149-1"
                  internal_item_type="Normal">
                  <internal_items />
                </InternalNormalItem>
              </MarkdownSegment>
            </paragraph_segments>
            <PrefixWSLength>0</PrefixWSLength>
            <SuffixWSLength>0</SuffixWSLength>
          </MarkdownLine>
        </Lines>
        <paragraph_segments>
          <MarkdownSegment
            trans_unit_id="147">
            <SegmentId>77c95b2f-6c1f-47b6-a9fa-df7bc9fd800d</SegmentId>
            <InternalNormalItem
              internal_item_id="1"
              internal_item_parent_id="147"
              trans_unit_id="147-1"
              internal_item_type="Normal">
              <internal_items />
            </InternalNormalItem>
          </MarkdownSegment>
          <MarkdownSegment
            trans_unit_id="148">
            <SegmentId>92a09384-dd9e-47c2-b98a-c9d44f7dce84</SegmentId>
            <InternalNormalItem
              internal_item_id="1"
              internal_item_parent_id="148"
              trans_unit_id="148-1"
              internal_item_type="Normal">
              <internal_items />
            </InternalNormalItem>
          </MarkdownSegment>
          <MarkdownSegment
            trans_unit_id="149">
            <SegmentId>e2e256d6-e8ce-4784-9a0e-70acad341335</SegmentId>
            <InternalNormalItem
              internal_item_id="1"
              internal_item_parent_id="149"
              trans_unit_id="149-1"
              internal_item_type="Normal">
              <internal_items />
            </InternalNormalItem>
          </MarkdownSegment>
        </paragraph_segments>
      </MarkdownBlockBase>
      <MarkdownBlockBase
        xsi:type="MarkdownParagraphBlock"
        item_id="a222ebee-898d-45f2-8eec-f3b47f601090"
        item_type="NormalParagraph"
        item_footer=""
        trans_unit_id="a222ebee-898d-45f2-8eec-f3b47f601090">
        <Lines>
          <MarkdownLine>
            <LineId>389468f7-1ab1-43bd-a01f-769ee1dc11af</LineId>
            <paragraph_segments>
              <MarkdownSegment
                trans_unit_id="150">
                <SegmentId>f8c66480-2334-4562-8274-16136e2c6029</SegmentId>
                <InternalNormalItem
                  internal_item_id="1"
                  internal_item_parent_id="150"
                  trans_unit_id="150-1"
                  internal_item_type="Normal">
                  <internal_items />
                </InternalNormalItem>
              </MarkdownSegment>
              <MarkdownSegment
                trans_unit_id="151">
                <SegmentId>bd68e33e-99d9-4490-a41d-064ed5eb7b33</SegmentId>
                <InternalNormalItem
                  internal_item_id="1"
                  internal_item_parent_id="151"
                  trans_unit_id="151-1"
                  internal_item_type="Normal">
                  <internal_items />
                </InternalNormalItem>
              </MarkdownSegment>
            </paragraph_segments>
            <PrefixWSLength>0</PrefixWSLength>
            <SuffixWSLength>0</SuffixWSLength>
          </MarkdownLine>
        </Lines>
        <paragraph_segments>
          <MarkdownSegment
            trans_unit_id="150">
            <SegmentId>f8c66480-2334-4562-8274-16136e2c6029</SegmentId>
            <InternalNormalItem
              internal_item_id="1"
              internal_item_parent_id="150"
              trans_unit_id="150-1"
              internal_item_type="Normal">
              <internal_items />
            </InternalNormalItem>
          </MarkdownSegment>
          <MarkdownSegment
            trans_unit_id="151">
            <SegmentId>bd68e33e-99d9-4490-a41d-064ed5eb7b33</SegmentId>
            <InternalNormalItem
              internal_item_id="1"
              internal_item_parent_id="151"
              trans_unit_id="151-1"
              internal_item_type="Normal">
              <internal_items />
            </InternalNormalItem>
          </MarkdownSegment>
        </paragraph_segments>
      </MarkdownBlockBase>
      <MarkdownBlockBase
        xsi:type="MarkdownParagraphBlock"
        item_id="3676420f-e4a2-4fc1-951a-698cee0bce12"
        item_type="NormalParagraph"
        item_footer=""
        trans_unit_id="3676420f-e4a2-4fc1-951a-698cee0bce12">
        <Lines>
          <MarkdownLine>
            <LineId>3937472f-f04d-4c8f-b0ef-ad617aa9b879</LineId>
            <paragraph_segments>
              <MarkdownSegment
                trans_unit_id="152">
                <SegmentId>ea4c1037-31a3-469e-a6b6-70f88d456eaa</SegmentId>
                <InternalNormalItem
                  internal_item_id="1"
                  internal_item_parent_id="152"
                  trans_unit_id="152-1"
                  internal_item_type="Normal">
                  <internal_items />
                </InternalNormalItem>
              </MarkdownSegment>
            </paragraph_segments>
            <PrefixWSLength>0</PrefixWSLength>
            <SuffixWSLength>0</SuffixWSLength>
          </MarkdownLine>
        </Lines>
        <paragraph_segments>
          <MarkdownSegment
            trans_unit_id="152">
            <SegmentId>ea4c1037-31a3-469e-a6b6-70f88d456eaa</SegmentId>
            <InternalNormalItem
              internal_item_id="1"
              internal_item_parent_id="152"
              trans_unit_id="152-1"
              internal_item_type="Normal">
              <internal_items />
            </InternalNormalItem>
          </MarkdownSegment>
        </paragraph_segments>
      </MarkdownBlockBase>
      <MarkdownBlockBase
        xsi:type="MarkdownHeaderBlock"
        item_id="5ba819c2-81e5-481a-affd-a251aef53cc9"
        item_type="Header"
        item_footer="footer_not_set"
        trans_unit_id="5ba819c2-81e5-481a-affd-a251aef53cc9">
        <segment
          trans_unit_id="153">
          <SegmentId>76b858e5-e66f-439e-9a7a-a40be7e0576c</SegmentId>
          <InternalNormalItem
            internal_item_id="1"
            internal_item_parent_id="153"
            trans_unit_id="153-1"
            internal_item_type="Normal">
            <internal_items />
          </InternalNormalItem>
        </segment>
        <header_type>Star</header_type>
        <header_level>2</header_level>
      </MarkdownBlockBase>
      <MarkdownBlockBase
        xsi:type="MarkdownParagraphBlock"
        item_id="568dad2f-8442-46ad-80e9-248a8f03ca59"
        item_type="NormalParagraph"
        item_footer=""
        trans_unit_id="568dad2f-8442-46ad-80e9-248a8f03ca59">
        <Lines>
          <MarkdownLine>
            <LineId>486fb446-7904-4309-afe4-54d39209b8b5</LineId>
            <paragraph_segments>
              <MarkdownSegment
                trans_unit_id="154">
                <SegmentId>46942150-5dad-4b53-8b8a-b5eb0c3054d0</SegmentId>
                <InternalNormalItem
                  internal_item_id="1"
                  internal_item_parent_id="154"
                  trans_unit_id="154-1"
                  internal_item_type="Normal">
                  <internal_items />
                </InternalNormalItem>
              </MarkdownSegment>
              <MarkdownSegment
                trans_unit_id="155">
                <SegmentId>3562a4da-dfd4-4151-abd9-004a03ca3925</SegmentId>
                <InternalNormalItem
                  internal_item_id="1"
                  internal_item_parent_id="155"
                  trans_unit_id="155-1"
                  internal_item_type="Normal">
                  <internal_items />
                </InternalNormalItem>
              </MarkdownSegment>
              <MarkdownSegment
                trans_unit_id="156">
                <SegmentId>f38727ec-d62b-4678-bae5-7fae187b01f1</SegmentId>
                <InternalNormalItem
                  internal_item_id="1"
                  internal_item_parent_id="156"
                  trans_unit_id="156-1"
                  internal_item_type="Normal">
                  <internal_items />
                </InternalNormalItem>
              </MarkdownSegment>
            </paragraph_segments>
            <PrefixWSLength>0</PrefixWSLength>
            <SuffixWSLength>0</SuffixWSLength>
          </MarkdownLine>
        </Lines>
        <paragraph_segments>
          <MarkdownSegment
            trans_unit_id="154">
            <SegmentId>46942150-5dad-4b53-8b8a-b5eb0c3054d0</SegmentId>
            <InternalNormalItem
              internal_item_id="1"
              internal_item_parent_id="154"
              trans_unit_id="154-1"
              internal_item_type="Normal">
              <internal_items />
            </InternalNormalItem>
          </MarkdownSegment>
          <MarkdownSegment
            trans_unit_id="155">
            <SegmentId>3562a4da-dfd4-4151-abd9-004a03ca3925</SegmentId>
            <InternalNormalItem
              internal_item_id="1"
              internal_item_parent_id="155"
              trans_unit_id="155-1"
              internal_item_type="Normal">
              <internal_items />
            </InternalNormalItem>
          </MarkdownSegment>
          <MarkdownSegment
            trans_unit_id="156">
            <SegmentId>f38727ec-d62b-4678-bae5-7fae187b01f1</SegmentId>
            <InternalNormalItem
              internal_item_id="1"
              internal_item_parent_id="156"
              trans_unit_id="156-1"
              internal_item_type="Normal">
              <internal_items />
            </InternalNormalItem>
          </MarkdownSegment>
        </paragraph_segments>
      </MarkdownBlockBase>
      <MarkdownBlockBase
        xsi:type="MarkdownParagraphBlock"
        item_id="170cdd37-d029-40ab-8bfb-11b8f2abc8e2"
        item_type="NormalParagraph"
        item_footer=""
        trans_unit_id="170cdd37-d029-40ab-8bfb-11b8f2abc8e2">
        <Lines>
          <MarkdownLine>
            <LineId>9ade6a7f-7f22-490e-9ab3-daad46b17603</LineId>
            <paragraph_segments>
              <MarkdownSegment
                trans_unit_id="157">
                <SegmentId>6ec181d4-4a36-4da8-891b-a1ec1150e606</SegmentId>
                <InternalNormalItem
                  internal_item_id="1"
                  internal_item_parent_id="157"
                  trans_unit_id="157-1"
                  internal_item_type="Normal">
                  <internal_items />
                </InternalNormalItem>
              </MarkdownSegment>
            </paragraph_segments>
            <PrefixWSLength>0</PrefixWSLength>
            <SuffixWSLength>0</SuffixWSLength>
          </MarkdownLine>
        </Lines>
        <paragraph_segments>
          <MarkdownSegment
            trans_unit_id="157">
            <SegmentId>6ec181d4-4a36-4da8-891b-a1ec1150e606</SegmentId>
            <InternalNormalItem
              internal_item_id="1"
              internal_item_parent_id="157"
              trans_unit_id="157-1"
              internal_item_type="Normal">
              <internal_items />
            </InternalNormalItem>
          </MarkdownSegment>
        </paragraph_segments>
      </MarkdownBlockBase>
      <MarkdownBlockBase
        xsi:type="MarkdownHeaderBlock"
        item_id="f9538c2b-7093-45dc-b889-451e8d657c6e"
        item_type="Header"
        item_footer="footer_not_set"
        trans_unit_id="f9538c2b-7093-45dc-b889-451e8d657c6e">
        <segment
          trans_unit_id="158">
          <SegmentId>4f461b9c-dc45-4636-9ae4-59294330bd91</SegmentId>
          <InternalNormalItem
            internal_item_id="1"
            internal_item_parent_id="158"
            trans_unit_id="158-1"
            internal_item_type="Normal">
            <internal_items />
          </InternalNormalItem>
        </segment>
        <header_type>Star</header_type>
        <header_level>2</header_level>
      </MarkdownBlockBase>
      <MarkdownBlockBase
        xsi:type="MarkdownParagraphBlock"
        item_id="1fd0903f-9994-44e2-b87a-dfaf5a6f7fab"
        item_type="NormalParagraph"
        item_footer="&#xA;"
        trans_unit_id="1fd0903f-9994-44e2-b87a-dfaf5a6f7fab">
        <Lines>
          <MarkdownLine>
            <LineId>6d96b273-4e2c-4b38-a6f3-5f6f9c861a5e</LineId>
            <paragraph_segments>
              <MarkdownSegment
                trans_unit_id="159">
                <SegmentId>8420511f-a8f0-41d2-99e4-6804759a7f29</SegmentId>
                <InternalNormalItem
                  internal_item_id="1"
                  internal_item_parent_id="159"
                  trans_unit_id="159-1"
                  internal_item_type="Normal">
                  <internal_items />
                </InternalNormalItem>
              </MarkdownSegment>
            </paragraph_segments>
            <PrefixWSLength>0</PrefixWSLength>
            <SuffixWSLength>1</SuffixWSLength>
          </MarkdownLine>
          <MarkdownLine>
            <LineId>adb629e0-525d-48a6-982f-55bc0b8cd345</LineId>
            <paragraph_segments>
              <MarkdownSegment
                trans_unit_id="160">
                <SegmentId>faffe675-6626-4107-8bd6-0f76d71f9c99</SegmentId>
                <InternalNormalItem
                  internal_item_id="1"
                  internal_item_parent_id="160"
                  trans_unit_id="160-1"
                  internal_item_type="Normal">
                  <internal_items />
                </InternalNormalItem>
                <MarkdownInternalHtmlTag
                  internal_item_id="2"
                  internal_item_parent_id="160"
                  trans_unit_id="160-2"
                  internal_item_type="HtmlTag">
                  <internal_items />
                  <itemValue>&lt;/iframe&gt;</itemValue>
                </MarkdownInternalHtmlTag>
              </MarkdownSegment>
            </paragraph_segments>
            <PrefixWSLength>0</PrefixWSLength>
            <SuffixWSLength>0</SuffixWSLength>
          </MarkdownLine>
        </Lines>
        <paragraph_segments>
          <MarkdownSegment
            trans_unit_id="159">
            <SegmentId>8420511f-a8f0-41d2-99e4-6804759a7f29</SegmentId>
            <InternalNormalItem
              internal_item_id="1"
              internal_item_parent_id="159"
              trans_unit_id="159-1"
              internal_item_type="Normal">
              <internal_items />
            </InternalNormalItem>
          </MarkdownSegment>
          <MarkdownSegment
            trans_unit_id="160">
            <SegmentId>faffe675-6626-4107-8bd6-0f76d71f9c99</SegmentId>
            <InternalNormalItem
              internal_item_id="1"
              internal_item_parent_id="160"
              trans_unit_id="160-1"
              internal_item_type="Normal">
              <internal_items />
            </InternalNormalItem>
            <MarkdownInternalHtmlTag
              internal_item_id="2"
              internal_item_parent_id="160"
              trans_unit_id="160-2"
              internal_item_type="HtmlTag">
              <internal_items />
              <itemValue>&lt;/iframe&gt;</itemValue>
            </MarkdownInternalHtmlTag>
          </MarkdownSegment>
        </paragraph_segments>
      </MarkdownBlockBase>
      <MarkdownBlockBase
        xsi:type="MarkdownHeaderBlock"
        item_id="b525af13-9712-438d-9cd6-f7561098ddee"
        item_type="Header"
        item_footer="footer_not_set"
        trans_unit_id="b525af13-9712-438d-9cd6-f7561098ddee">
        <segment
          trans_unit_id="161">
          <SegmentId>3bcb47f2-54f4-424b-908a-1d1013d11006</SegmentId>
          <InternalNormalItem
            internal_item_id="1"
            internal_item_parent_id="161"
            trans_unit_id="161-1"
            internal_item_type="Normal">
            <internal_items />
          </InternalNormalItem>
        </segment>
        <header_type>Star</header_type>
        <header_level>2</header_level>
      </MarkdownBlockBase>
      <MarkdownBlockBase
        xsi:type="MarkdownParagraphBlock"
        item_id="3136145b-50f8-4401-b7cd-75cb42a81bf3"
        item_type="NormalParagraph"
        item_footer=""
        trans_unit_id="3136145b-50f8-4401-b7cd-75cb42a81bf3">
        <Lines>
          <MarkdownLine>
            <LineId>27a586b6-dee4-48ac-8421-ebae88f217e4</LineId>
            <paragraph_segments>
              <MarkdownSegment
                trans_unit_id="162">
                <SegmentId>3ea29794-1e05-4598-8072-bd82acda33e4</SegmentId>
                <LinkItem
                  internal_item_id="1"
                  internal_item_parent_id="162"
                  trans_unit_id="162-1"
                  internal_item_type="Link">
                  <internal_items />
                  <internal_link_type>Inline</internal_link_type>
                  <internal_link_text>Get started with Windows Server Containers in Windows Azure</internal_link_text>
                  <internal_link_url>../quick_start/azure_setup.md</internal_link_url>
                  <internal_link_title />
                </LinkItem>
              </MarkdownSegment>
            </paragraph_segments>
            <PrefixWSLength>0</PrefixWSLength>
            <SuffixWSLength>2</SuffixWSLength>
          </MarkdownLine>
          <MarkdownLine>
            <LineId>e84dcb42-b837-4a3d-b256-323c6b658d9c</LineId>
            <paragraph_segments>
              <MarkdownSegment
                trans_unit_id="163">
                <SegmentId>6fc6f0c3-7afd-45ae-9de5-0dbf7c3de6b1</SegmentId>
                <LinkItem
                  internal_item_id="1"
                  internal_item_parent_id="163"
                  trans_unit_id="163-1"
                  internal_item_type="Link">
                  <internal_items />
                  <internal_link_type>Inline</internal_link_type>
                  <internal_link_text>Get started with Windows Server Containers Locally</internal_link_text>
                  <internal_link_url>../quick_start/container_setup.md</internal_link_url>
                  <internal_link_title />
                </LinkItem>
              </MarkdownSegment>
            </paragraph_segments>
            <PrefixWSLength>0</PrefixWSLength>
            <SuffixWSLength>0</SuffixWSLength>
          </MarkdownLine>
        </Lines>
        <paragraph_segments>
          <MarkdownSegment
            trans_unit_id="162">
            <SegmentId>3ea29794-1e05-4598-8072-bd82acda33e4</SegmentId>
            <LinkItem
              internal_item_id="1"
              internal_item_parent_id="162"
              trans_unit_id="162-1"
              internal_item_type="Link">
              <internal_items />
              <internal_link_type>Inline</internal_link_type>
              <internal_link_text>Get started with Windows Server Containers in Windows Azure</internal_link_text>
              <internal_link_url>../quick_start/azure_setup.md</internal_link_url>
              <internal_link_title />
            </LinkItem>
          </MarkdownSegment>
          <MarkdownSegment
            trans_unit_id="163">
            <SegmentId>6fc6f0c3-7afd-45ae-9de5-0dbf7c3de6b1</SegmentId>
            <LinkItem
              internal_item_id="1"
              internal_item_parent_id="163"
              trans_unit_id="163-1"
              internal_item_type="Link">
              <internal_items />
              <internal_link_type>Inline</internal_link_type>
              <internal_link_text>Get started with Windows Server Containers Locally</internal_link_text>
              <internal_link_url>../quick_start/container_setup.md</internal_link_url>
              <internal_link_title />
            </LinkItem>
          </MarkdownSegment>
        </paragraph_segments>
      </MarkdownBlockBase>
      <MarkdownBlockBase
        xsi:type="MarkdownHorizonalRuleBlock"
        item_id="bd42b47e-11da-4270-aec8-950d431f7260"
        item_type="HorizontalRule"
        item_footer="footer_not_set"
        trans_unit_id="bd42b47e-11da-4270-aec8-950d431f7260">
        <horizonal_rule>-------------------</horizonal_rule>
      </MarkdownBlockBase>
      <MarkdownBlockBase
        xsi:type="MarkdownParagraphBlock"
        item_id="974d9418-6796-4272-b3df-c8d15863dd4a"
        item_type="NormalParagraph"
        item_footer="&#xA;&#xA;"
        trans_unit_id="974d9418-6796-4272-b3df-c8d15863dd4a">
        <Lines>
          <MarkdownLine>
            <LineId>dd21e009-8ee1-4750-8a40-fb1a6725b986</LineId>
            <paragraph_segments>
              <MarkdownSegment
                trans_unit_id="164">
                <SegmentId>8a4af16e-1544-423b-ac22-847bd6a994b0</SegmentId>
                <LinkItem
                  internal_item_id="1"
                  internal_item_parent_id="164"
                  trans_unit_id="164-1"
                  internal_item_type="Link">
                  <internal_items />
                  <internal_link_type>Inline</internal_link_type>
                  <internal_link_text>Back to Container Home</internal_link_text>
                  <internal_link_url>../containers_welcome.md</internal_link_url>
                  <internal_link_title />
                </LinkItem>
              </MarkdownSegment>
            </paragraph_segments>
            <PrefixWSLength>0</PrefixWSLength>
            <SuffixWSLength>0</SuffixWSLength>
          </MarkdownLine>
        </Lines>
        <paragraph_segments>
          <MarkdownSegment
            trans_unit_id="164">
            <SegmentId>8a4af16e-1544-423b-ac22-847bd6a994b0</SegmentId>
            <LinkItem
              internal_item_id="1"
              internal_item_parent_id="164"
              trans_unit_id="164-1"
              internal_item_type="Link">
              <internal_items />
              <internal_link_type>Inline</internal_link_type>
              <internal_link_text>Back to Container Home</internal_link_text>
              <internal_link_url>../containers_welcome.md</internal_link_url>
              <internal_link_title />
            </LinkItem>
          </MarkdownSegment>
        </paragraph_segments>
      </MarkdownBlockBase>
    </ArrayOfMarkdownBlockBase>
  </block_element>
  <references>
    <ArrayOfMarkdownLinkedReference xmlns:xsd="http://www.w3.org/2001/XMLSchema" xmlns:xsi="http://www.w3.org/2001/XMLSchema-instance" />
  </references>
</markdown_skeleton_root>